Workbook
Name Slicer_Category1: #N/A
Name Slicer_Expense_Amount: #N/A
Name Slicer_Expense_Category: #N/A
Name Slicer_Income_Source: #N/A
Name Slicer_Month: #N/A

Sheet Welcome Page
C2: 💰 PERSONAL FINANCE & BUDGET PLANNER
C5: -------EXECUTIVE DASHBOARD & FINANCIAL ANALYTICS SYSTEM-------
C9: WELCOME | J9: Project Name | M9: Personal Finance & Budget Planner | S9: “Do not save what is left after spending, spend what is left after saving.” — Warren Buffett
J11: Developed By | M11: Abhijit Roy & Aakash Nath
C13: •Track • Analyze • Save • Grow | J13: Technology | M13: Microsoft Excel
J15: Features | M15: KPI Dashboard, Pivot Analysis, Budget Tracking & Insights
J17: Academic Year | M17: 2026
J19: Institute | M19: Anudip Foundation, COE
C22: START DASHBOARD | F22: VIEW RAW DATA | J22: INCOME ANALYSIS | M22: EXPENSE ANALYSIS | P22: PIVOT ANALYSIS
C27: © 2025 Personal Finance & Budget Planner | Developed using Microsoft Excel 🗝️

Sheet Raw Data
A1: RAW DATA | O1: Go to Welcome Page
A2: Id | B2: Date | C2: Month | D2: Person Name | E2: Age | F2: City | G2: Income Source | H2: Monthly Income | I2: ExpenseCategory | J2: Expense Amount | K2: Payment Method | L2: Savings | M2: Loan EMI | N2: Credit Score | O2: Financial Status
A3: TXN1001 | B3: 45659 | C3: January | D3: Rahul Sen | E3: 29 | F3: Kolkata | G3: Salary | H3: 65000 | I3: Rent | J3: 18000 | K3: UPI | L3: 12000 | M3: 5000 | N3: 742 | O3: Stable
A4: TXN1002 | B4: 45660 | C4: February | D4: Priya Das | E4: 34 | F4: Mumbai | G4: Freelancing | H4: 72000 | I4: Groceries | J4: 6500 | K4: Card | L4: 15000 | N4: 788 | O4: Good
A5: TXN1003 | B5: 45661 | C5: March | D5: Ankit Roy | E5: 26 | G5: Salary | H5: 54000 | J5: 3200 | K5: Cash | L5: 8000 | M5: 2500 | N5: 689 | O5: Average
A6: TXN1004 | B6: 45662 | C6: April | D6: Sneha Paul | E6: 31 | F6: Bangalore | G6: Business | H6: 98000 | I6: Utilities | J6: 5400 | K6: NetBanking | L6: 25000 | M6: 8000 | N6: 801 | O6: Excellent
A7: TXN1005 | B7: 45663 | C7: May | D7: Rohan Mitra | E7: 38 | F7: Hyderabad | G7: Salary | H7: 85000 | I7: Entertainment | J7: 7600 | K7: Card | L7: 10000 | M7: 12000 | N7: 655 | O7: Risky
A8: TXN1006 | B8: 45664 | C8: June | D8: Aditi Sharma | E8: 27 | F8: Pune | H8: 61000 | I8: Healthcare | J8: 2400 | K8: UPI | L8: 17000 | N8: 771 | O8: Good
A9: TXN1007 | B9: 45665 | C9: July | D9: Karan Singh | E9: 42 | F9: Chennai | G9: Business | H9: 120000 | I9: Rent | J9: 25000 | K9: Cheque | L9: 35000 | M9: 18000 | N9: 720 | O9: Stable
A10: TXN1008 | B10: 45666 | C10: August | D10: Megha Dutta | E10: 24 | F10: Kolkata | G10: Internship | H10: 28000 | I10: Education | J10: 4500 | K10: UPI | L10: 5000 | N10: 690 | O10: Average
A11: TXN1009 | B11: 45667 | C11: September | D11: Arjun Nair | E11: 36 | F11: Kochi | G11: Salary | H11: 76000 | J11: 8200 | K11: Card | L11: 14000 | M11: 7000 | N11: 745 | O11: Stable
A12: TXN1010 | B12: 45668 | C12: October | D12: Neha Kapoor | E12: 30 | F12: Jaipur | G12: Freelancing | H12: 68000 | I12: Shopping | J12: 9200 | K12: UPI | L12: 11000 | M12: 3000 | N12: 732 | O12: Good
A13: TXN1011 | B13: 45669 | C13: November | D13: Vikram Bose | E13: 45 | F13: Kolkata | G13: Business | H13: 150000 | I13: Investment | J13: 35000 | K13: NetBanking | L13: 40000 | M13: 20000 | N13: 810 | O13: Excellent
A14: TXN1012 | B14: 45670 | C14: December | D14: Isha Jain | E14: 28 | F14: Delhi | H14: 59000 | I14: Food | J14: 5800 | L14: 9000 | M14: 2500 | N14: 704 | O14: Stable
A15: TXN1013 | B15: 45671 | C15: January | D15: Sourav Ghosh | E15: 33 | G15: Salary | H15: 71000 | I15: Rent | J15: 21000 | K15: UPI | L15: 13000 | M15: 6000 | N15: 740 | O15: Good
A16: TXN1014 | B16: 45672 | C16: February | D16: Ritika Sen | E16: 25 | F16: Pune | G16: Freelancing | H16: 47000 | I16: Entertainment | J16: 4200 | K16: Card | L16: 7000 | N16: 681 | O16: Average
A17: TXN1015 | B17: 45673 | C17: March | D17: Abhishek Das | E17: 39 | F17: Bangalore | G17: Business | H17: 132000 | I17: Healthcare | J17: 6800 | K17: NetBanking | L17: 30000 | M17: 15000 | N17: 790 | O17: Excellent
A18: TXN1016 | B18: 45674 | C18: April | D18: Nikita Roy | E18: 29 | F18: Delhi | G18: Salary | H18: 62000 | I18: Groceries | J18: 5900 | K18: UPI | L18: 12000 | M18: 3000 | N18: 725 | O18: Good
A19: TXN1017 | B19: 45675 | C19: May | D19: Manish Yadav | E19: 35 | F19: Mumbai | G19: Salary | H19: 81000 | I19: Transport | J19: 4100 | K19: Cash | L19: 16000 | M19: 9000 | N19: 710 | O19: Stable
A20: TXN1018 | B20: 45676 | C20: June | D20: Simran Kaur | E20: 27 | F20: Chandigarh | G20: Freelancing | H20: 56000 | J20: 9700 | K20: Card | L20: 8500 | N20: 699 | O20: Average
A21: TXN1019 | B21: 45677 | C21: July | D21: Raj Malhotra | E21: 41 | F21: Delhi | G21: Business | H21: 145000 | I21: Utilities | J21: 7800 | K21: Cheque | L21: 42000 | M21: 25000 | N21: 805 | O21: Excellent
A22: TXN1020 | B22: 45678 | C22: August | D22: Pooja Mehta | E22: 32 | F22: Ahmedabad | G22: Salary | H22: 69000 | I22: Food | J22: 6300 | K22: UPI | L22: 10000 | M22: 4500 | N22: 730 | O22: Good
A23: TXN1021 | B23: 45679 | C23: September | D23: Deepak Kumar | E23: 37 | F23: Patna | G23: Salary | H23: 57000 | I23: Rent | J23: 16000 | K23: Cash | L23: 6000 | M23: 5500 | N23: 670 | O23: Risky
A24: TXN1022 | B24: 45680 | C24: October | D24: Tanvi Shah | E24: 26 | F24: Surat | G24: Freelancing | H24: 52000 | I24: Shopping | J24: 7600 | K24: Card | L24: 9000 | N24: 715 | O24: Stable
A25: TXN1023 | B25: 45681 | C25: November | D25: Ritesh Verma | E25: 40 | H25: 125000 | I25: Investment | J25: 28000 | K25: NetBanking | L25: 37000 | M25: 12000 | N25: 798 | O25: Excellent
A26: TXN1024 | B26: 45682 | C26: December | D26: Ananya Ghosh | E26: 31 | F26: Kolkata | G26: Salary | H26: 74000 | I26: Education | J26: 5300 | K26: UPI | L26: 15000 | M26: 5000 | N26: 750 | O26: Good
A27: TXN1025 | B27: 45683 | C27: January | D27: Kunal Sharma | E27: 28 | F27: Delhi | G27: Salary | H27: 63000 | J27: 8600 | K27: Card | L27: 11000 | M27: 3500 | N27: 721 | O27: Stable
A28: TXN1075 | B28: 45733 | C28: February | D28: Amit Bose | E28: 36 | F28: Kolkata | G28: Salary | H28: 81000 | I28: Travel | J28: 9400 | K28: UPI | L28: 17000 | M28: 8500 | N28: 743 | O28: Good
A29: TXN1076 | B29: 45734 | C29: March | D29: Sonia Jain | E29: 27 | F29: Pune | G29: Freelancing | H29: 55000 | I29: Food | J29: 5200 | K29: Card | L29: 8000 | N29: 701 | O29: Stable
A30: TXN1077 | B30: 45735 | C30: April | D30: Harsh Vardhan | E30: 43 | F30: Delhi | G30: Business | H30: 149000 | I30: Investment | J30: 41000 | K30: Cheque | L30: 50000 | M30: 23000 | N30: 815 | O30: Excellent
A31: TXN1078 | B31: 45736 | C31: May | D31: Ankita Sen | E31: 30 | F31: Kolkata | G31: Salary | H31: 72000 | I31: Utilities | J31: 6300 | K31: UPI | L31: 14500 | M31: 3500 | N31: 735 | O31: Good
A32: TXN1079 | B32: 45737 | C32: June | D32: Rohan Sharma | E32: 28 | F32: Delhi | G32: Salary | H32: 65000 | I32: Transport | J32: 4800 | K32: Cash | L32: 10000 | M32: 4000 | N32: 712 | O32: Stable
A33: TXN1080 | B33: 45738 | C33: July | D33: Priya Roy | E33: 25 | F33: Kolkata | G33: Freelancing | H33: 50000 | I33: Shopping | J33: 8100 | K33: Card | L33: 6000 | N33: 689 | O33: Average
A34: TXN1081 | B34: 45739 | C34: August | D34: Abhishek Jain | E34: 40 | F34: Mumbai | H34: 137000 | I34: Rent | J34: 33000 | L34: 41000 | M34: 17000 | N34: 799 | O34: Excellent
A35: TXN1082 | B35: 45740 | C35: September | D35: Tania Das | E35: 31 | F35: Kolkata | G35: Salary | H35: 70000 | I35: Healthcare | J35: 4600 | K35: UPI | L35: 13000 | M35: 3000 | N35: 732 | O35: Good
A36: TXN1083 | B36: 45741 | C36: October | D36: Manish Roy | E36: 35 | F36: Delhi | G36: Salary | H36: 83000 | I36: Travel | J36: 10200 | K36: Card | L36: 18000 | M36: 9500 | N36: 747 | O36: Good
A37: TXN1084 | B37: 45742 | C37: November | D37: Sweta Kapoor | E37: 26 | F37: Pune | G37: Freelancing | H37: 53000 | I37: Entertainment | J37: 4100 | K37: Cash | L37: 7000 | N37: 694 | O37: Average
A38: TXN1085 | B38: 45743 | C38: December | D38: Kunal Verma | E38: 42 | F38: Ahmedabad | G38: Business | H38: 144000 | I38: Investment | J38: 37000 | K38: Cheque | L38: 46000 | M38: 21000 | N38: 810 | O38: Excellent
A39: TXN1086 | B39: 45744 | C39: January | D39: Megha Roy | E39: 29 | F39: Kolkata | G39: Salary | H39: 69000 | I39: Groceries | J39: 6200 | K39: UPI | L39: 12500 | M39: 3000 | N39: 728 | O39: Good
A40: TXN1087 | B40: 45745 | C40: February | D40: Rajat Das | E40: 33 | G40: Salary | H40: 78000 | I40: Rent | J40: 22000 | K40: Card | L40: 15000 | M40: 7000 | N40: 739 | O40: Good
A41: TXN1088 | B41: 45746 | C41: March | D41: Sneha Kapoor | E41: 24 | F41: Kolkata | G41: Internship | H41: 30000 | I41: Food | J41: 3500 | K41: Cash | L41: 4000 | N41: 680 | O41: Average
A42: TXN1089 | B42: 45747 | C42: April | D42: Arvind Sharma | E42: 45 | F42: Bangalore | G42: Business | H42: 158000 | I42: Healthcare | J42: 9100 | K42: NetBanking | L42: 54000 | M42: 8000 | N42: 822 | O42: Excellent
A43: TXN1090 | B43: 45748 | C43: May | D43: Neha Das | E43: 30 | F43: Kolkata | H43: 73000 | I43: Shopping | J43: 7900 | L43: 13500 | M43: 4000 | N43: 736 | O43: Good
A44: TXN1091 | B44: 45749 | C44: June | D44: Rahul Mehta | E44: 36 | F44: Mumbai | G44: Salary | H44: 86000 | J44: 9700 | K44: Card | L44: 19000 | M44: 10000 | N44: 748 | O44: Good
A45: TXN1092 | B45: 45750 | C45: July | D45: Priyanka Roy | E45: 27 | F45: Kolkata | G45: Freelancing | H45: 52000 | I45: Entertainment | J45: 4500 | K45: UPI | L45: 6500 | N45: 696 | O45: Average
A46: TXN1093 | B46: 45751 | C46: August | D46: Vikas Jain | E46: 41 | F46: Delhi | G46: Business | H46: 139000 | I46: Investment | J46: 35000 | K46: Cheque | L46: 42000 | M46: 18000 | N46: 801 | O46: Excellent
A47: TXN1094 | B47: 45752 | C47: September | D47: Sohini Sen | E47: 31 | F47: Kolkata | G47: Salary | H47: 71000 | I47: Utilities | J47: 6100 | K47: Card | L47: 14000 | M47: 3500 | N47: 734 | O47: Good
A48: TXN1095 | B48: 45753 | C48: October | D48: Ankit Sharma | E48: 28 | G48: Salary | H48: 67000 | I48: Rent | J48: 19500 | K48: UPI | L48: 10500 | M48: 4500 | N48: 718 | O48: Stable
A49: TXN1096 | B49: 45754 | C49: November | D49: Tina Roy | E49: 25 | F49: Kolkata | G49: Internship | H49: 31000 | I49: Education | J49: 3900 | K49: Cash | L49: 3000 | N49: 677 | O49: Average
A50: TXN1097 | B50: 45755 | C50: December | D50: Rakesh Gupta | E50: 43 | F50: Ahmedabad | G50: Business | H50: 148000 | I50: Healthcare | J50: 8300 | K50: NetBanking | L50: 49000 | M50: 22000 | N50: 814 | O50: Excellent
A51: TXN1098 | B51: 45756 | C51: January | D51: Pallabi Das | E51: 30 | F51: Kolkata | G51: Salary | H51: 72000 | I51: Shopping | J51: 7400 | K51: UPI | L51: 13200 | M51: 3000 | N51: 731 | O51: Good
A52: TXN1099 | B52: 45757 | C52: February | D52: Sumit Roy | E52: 35 | F52: Delhi | H52: 80000 | I52: Travel | J52: 10100 | K52: Card | L52: 17500 | M52: 9000 | N52: 744 | O52: Good
A53: TXN1100 | B53: 45758 | C53: March | D53: Ayesha Khan | E53: 27 | F53: Kolkata | G53: Freelancing | H53: 54000 | I53: Food | J53: 5100 | K53: UPI | L53: 7200 | N53: 700 | O53: Stable
A54: TXN1026 | B54: 45684 | C54: April | D54: Shreya Banerjee | E54: 30 | F54: Kolkata | G54: Salary | H54: 67000 | I54: Healthcare | J54: 3400 | K54: UPI | L54: 14000 | M54: 2500 | N54: 738 | O54: Good
A55: TXN1027 | B55: 45685 | C55: May | D55: Aman Verma | E55: 27 | F55: Delhi | G55: Freelancing | H55: 51000 | J55: 4700 | K55: Cash | L55: 6000 | N55: 688 | O55: Average
A56: TXN1028 | B56: 45686 | C56: June | D56: Niharika Bose | E56: 35 | F56: Bangalore | G56: Business | H56: 118000 | I56: Rent | J56: 28000 | L56: 32000 | M56: 14000 | N56: 799 | O56: Excellent
A57: TXN1029 | B57: 45687 | C57: July | D57: Rajeev Kumar | E57: 44 | G57: Salary | H57: 83000 | I57: Utilities | J57: 7200 | K57: NetBanking | L57: 18000 | M57: 10000 | N57: 712 | O57: Stable
A58: TXN1030 | B58: 45688 | C58: August | D58: Anjali Roy | E58: 26 | F58: Kolkata | G58: Internship | H58: 31000 | I58: Education | J58: 3800 | K58: UPI | L58: 4500 | N58: 675 | O58: Average
A59: TXN1031 | B59: 45689 | C59: September | D59: Sahil Mehta | E59: 33 | F59: Mumbai | G59: Salary | H59: 78000 | I59: Travel | J59: 9100 | K59: Card | L59: 13000 | M59: 5000 | N59: 741 | O59: Good
A60: TXN1032 | B60: 45690 | C60: October | D60: Ritu Sharma | E60: 29 | F60: Jaipur | G60: Freelancing | H60: 56000 | I60: Shopping | J60: 6900 | K60: UPI | L60: 8000 | M60: 7000 | N60: 701 | O60: Stable
A61: TXN1033 | B61: 45691 | C61: November | D61: Vivek Singh | E61: 39 | F61: Delhi | H61: 138000 | I61: Investment | J61: 32000 | K61: NetBanking | L61: 41000 | M61: 18000 | N61: 807 | O61: Excellent
A62: TXN1034 | B62: 45692 | C62: December | D62: Pallavi Das | E62: 31 | F62: Kolkata | G62: Salary | H62: 69000 | I62: Groceries | J62: 6400 | K62: Card | L62: 12000 | M62: 3000 | N62: 728 | O62: Good
A63: TXN1035 | B63: 45693 | C63: January | D63: Arindam Sen | E63: 28 | F63: Kolkata | G63: Salary | H63: 62000 | I63: Rent | J63: 19000 | K63: UPI | L63: 10000 | M63: 4000 | N63: 719 | O63: Stable
A64: TXN1036 | B64: 45694 | C64: February | D64: Neeraj Kapoor | E64: 36 | F64: Delhi | G64: Salary | H64: 87000 | I64: Transport | J64: 4300 | K64: Cash | L64: 17000 | M64: 8500 | N64: 734 | O64: Good
A65: TXN1037 | B65: 45695 | C65: March | D65: Komal Jain | E65: 24 | F65: Pune | G65: Internship | H65: 29000 | I65: Entertainment | J65: 3600 | K65: UPI | L65: 3000 | N65: 682 | O65: Average
A66: TXN1038 | B66: 45696 | C66: April | D66: Harsh Patel | E66: 41 | F66: Ahmedabad | G66: Business | H66: 128000 | I66: Healthcare | J66: 7600 | K66: Cheque | L66: 35000 | M66: 16000 | N66: 792 | O66: Excellent
A67: TXN1039 | B67: 45697 | C67: May | D67: Sonia Gupta | E67: 32 | G67: Salary | H67: 71000 | J67: 6100 | K67: Card | L67: 11000 | M67: 4500 | N67: 725 | O67: Good
A68: TXN1040 | C68: June | D68: Rahul Sen | E68: 29 | F68: Kolkatta | G68: Salary | H68: 65000 | I68: Rent | J68: 18000 | K68: UPI | M68: 5000 | N68: 742 | O68: Stable
A69: TXN1041 | B69: 45699 | C69: July | D69: Tina Dey | E69: 27 | F69: Kolkata | G69: Freelancing | H69: 53000 | I69: Shopping | J69: 7900 | K69: UPI | L69: 7000 | N69: 695 | O69: Average
A70: TXN1042 | B70: 45700 | C70: August | D70: Aditya Rao | E70: 38 | F70: Hyderabad | G70: Salary | H70: 92000 | I70: Travel | J70: 10400 | K70: Card | L70: 20000 | M70: 12000 | N70: 755 | O70: Good
A71: TXN1043 | B71: 45701 | C71: September | D71: Meenakshi Iyer | E71: 34 | F71: Chennai | G71: Business | H71: 142000 | I71: Investment | J71: 36000 | K71: NetBanking | L71: 45000 | M71: 20000 | N71: 812 | O71: Excellent
A72: TXN1044 | B72: 45702 | C72: October | D72: Rakesh Yadav | E72: 43 | F72: Patna | G72: Salary | H72: 61000 | I72: Utilities | J72: 5900 | K72: Cash | L72: 8000 | M72: 7000 | N72: 676 | O72: Risky
A73: TXN1045 | B73: 45703 | C73: November | D73: Swati Ghosh | E73: 29 | F73: Kolkata | H73: 73000 | I73: Healthcare | J73: 4100 | K73: UPI | L73: 15000 | M73: 3000 | N73: 744 | O73: Good
A74: TXN1046 | B74: 45704 | C74: December | D74: Imran Ali | E74: 37 | F74: Mumbai | G74: Freelancing | H74: 64000 | I74: Food | J74: 5600 | K74: Card | L74: 12000 | M74: 2500 | N74: 718 | O74: Stable
A75: TXN1047 | B75: 45705 | C75: January | D75: Priyanka Sen | E75: 26 | F75: Delhi | G75: Salary | H75: 58000 | I75: Education | J75: 6200 | K75: UPI | L75: 9000 | M75: 9800 | N75: 708 | O75: Stable
A76: TXN1048 | B76: 45706 | C76: February | D76: Ajay Malhotra | E76: 45 | F76: Bangalore | G76: Business | H76: 155000 | I76: Rent | J76: 34000 | L76: 50000 | M76: 22000 | N76: 820 | O76: Excellent
A77: TXN1049 | B77: 45707 | C77: March | D77: Nupur Das | E77: 30 | F77: Kolkata | G77: Salary | H77: 70000 | I77: Entertainment | J77: 5300 | K77: Card | L77: 13000 | M77: 3500 | N77: 731 | O77: Good
A78: TXN1050 | B78: 45708 | C78: April | D78: Karan Oberoi | E78: 35 | F78: Delhi | G78: Salary | H78: 84000 | I78: Transport | J78: 4800 | K78: Cash | L78: 16000 | M78: 9000 | N78: 726 | O78: Stable
A79: TXN1051 | B79: 45709 | C79: May | D79: Shivani Roy | E79: 28 | G79: Freelancing | H79: 55000 | I79: Shopping | J79: 8300 | K79: UPI | L79: 8500 | N79: 699 | O79: Average
A80: TXN1052 | B80: 45710 | C80: June | D80: Manav Jain | E80: 40 | F80: Ahmedabad | G80: Business | H80: 134000 | I80: Investment | J80: 31000 | K80: NetBanking | L80: 39000 | M80: 17000 | N80: 803 | O80: Excellent
A81: TXN1053 | B81: 45711 | C81: July | D81: Snehal Patil | E81: 31 | F81: Mumbai | G81: Salary | H81: 76000 | I81: Groceries | J81: 6800 | K81: Card | L81: 14000 | M81: 4000 | N81: 739 | O81: Good
A82: TXN1054 | B82: 45712 | C82: August | D82: Rohit Das | E82: 27 | F82: Kolkata | G82: Salary | H82: 61000 | I82: Rent | J82: 17500 | K82: UPI | L82: 10000 | M82: 3500 | N82: 714 | O82: Stable
A83: TXN1055 | B83: 45713 | C83: September | D83: Ananya Kapoor | E83: 33 | F83: Delhi | G83: Salary | H83: 85000 | I83: Healthcare | J83: 5200 | K83: NetBanking | L83: 18000 | M83: 8000 | N83: 748 | O83: Good
A84: TXN1056 | B84: 45714 | C84: October | D84: Deep Roy | E84: 24 | F84: Kolkata | G84: Internship | H84: 27000 | I84: Food | J84: 3900 | K84: Cash | L84: 2500 | N84: 671 | O84: Average
A85: TXN1057 | B85: 45715 | C85: November | D85: Tarun Singh | E85: 39 | F85: Chandigarh | H85: 126000 | I85: Travel | J85: 11200 | K85: Card | L85: 32000 | M85: 15000 | N85: 791 | O85: Excellent
A86: TXN1058 | B86: 45716 | C86: December | D86: Pooja Sharma | E86: 29 | F86: Jaipur | G86: Salary | H86: 68000 | I86: Shopping | J86: 7200 | K86: UPI | L86: 12000 | M86: 2500 | N86: 733 | O86: Good
A87: TXN1059 | B87: 45717 | C87: January | D87: Abhinav Bose | E87: 36 | F87: Kolkata | G87: Salary | H87: 79000 | I87: Utilities | J87: 6100 | K87: Card | L87: 17000 | M87: 6500 | N87: 742 | O87: Good
A88: TXN1060 | B88: 45718 | C88: February | D88: Ritika Das | E88: 25 | F88: Pune | G88: Freelancing | H88: 49000 | I88: Entertainment | J88: 4700 | L88: 6000 | M88: 8000 | N88: 687 | O88: Average
A89: TXN1061 | B89: 45719 | C89: March | D89: Vinay Kumar | E89: 42 | F89: Patna | G89: Business | H89: 146000 | I89: Investment | J89: 39000 | K89: Cheque | L89: 47000 | M89: 21000 | N89: 809 | O89: Excellent
A90: TXN1062 | B90: 45720 | C90: April | D90: Neha Sen | E90: 31 | F90: Kolkata | G90: Salary | H90: 71000 | I90: Healthcare | J90: 4500 | K90: UPI | L90: 14000 | M90: 3500 | N90: 737 | O90: Good
A91: TXN1063 | B91: 45721 | C91: May | D91: Rajat Sharma | E91: 28 | G91: Salary | H91: 64000 | I91: Transport | J91: 5100 | K91: Cash | L91: 11000 | M91: 4000 | N91: 716 | O91: Stable
A92: TXN1064 | B92: 45722 | C92: June | D92: Ishita Roy | E92: 27 | F92: Kolkata | G92: Freelancing | H92: 54000 | I92: Food | J92: 5900 | K92: Card | L92: 7000 | N92: 697 | O92: Average
A93: TXN1065 | B93: 45723 | C93: July | D93: Sandeep Jain | E93: 44 | F93: Mumbai | G93: Business | H93: 152000 | I93: Rent | J93: 36000 | K93: NetBanking | L93: 52000 | M93: 24000 | N93: 818 | O93: Excellent
A94: TXN1066 | B94: 45724 | C94: August | D94: Monika Gupta | E94: 30 | F94: Delhi | H94: 73000 | I94: Shopping | J94: 8400 | K94: UPI | L94: 13000 | M94: 5000 | N94: 729 | O94: Good
A95: TXN1067 | B95: 45725 | C95: September | D95: Arjun Das | E95: 35 | F95: Kolkata | G95: Salary | H95: 82000 | I95: Travel | J95: 9800 | K95: Card | L95: 19000 | M95: 9000 | N95: 745 | O95: Good
A96: TXN1068 | B96: 45726 | C96: October | D96: Preeti Nair | E96: 26 | F96: Kochi | G96: Freelancing | H96: 51000 | J96: 4300 | K96: UPI | L96: 6500 | M96: 7000 | N96: 692 | O96: Average
A97: TXN1069 | B97: 45727 | C97: November | D97: Kishore Patel | E97: 41 | F97: Ahmedabad | G97: Business | H97: 129000 | I97: Investment | J97: 30000 | K97: Cheque | L97: 36000 | M97: 16000 | N97: 796 | O97: Excellent
A98: TXN1070 | B98: 45728 | C98: December | D98: Simran Das | E98: 32 | F98: Kolkata | G98: Salary | H98: 69000 | I98: Groceries | J98: 6700 | K98: Card | L98: 12500 | M98: 3000 | N98: 734 | O98: Good
A99: TXN1071 | B99: 45729 | C99: January | D99: Aditya Singh | E99: 29 | F99: Delhi | G99: Salary | H99: 66000 | I99: Rent | J99: 20000 | K99: UPI | L99: 9000 | M99: 4500 | N99: 710 | O99: Stable
A100: TXN1072 | B100: 45730 | C100: February | D100: Payal Roy | E100: 24 | H100: 32000 | J100: 3900 | L100: 3500 | N100: 678 | O100: Average

Sheet Cleaning Tasks
A1: DATA CLEANING PROCESS
A2: Id | B2: Date | C2: Month | D2: Person Name | E2: Age | F2: City | G2: Income Source | H2: Monthly Income | I2: Expense Category | J2: Expense Amount | K2: Payment Method | L2: Savings | M2: Loan EMI | N2: Credit Score | O2: Financial Status | P2: City2 | Q2: Income Source2 | R2: Expense Category2 | S2: Loan EMI2 | T2: Payment Method2
A3: TXN1001 | B3: 45659 | C3: January | D3: Rahul Sen | E3: 29 | F3: Kolkata | G3: Salary | H3: 65000 | I3: Rent | J3: 18000 | K3: UPI | L3: 12000 | M3: 5000 | N3: 742 | O3: Stable | P3: =IF(COUNTBLANK(F3)=0,F3,"Unknown") -> Kolkata | Q3: =IF(COUNTBLANK(G3)=0,G3,"Unknown") -> Salary | R3: =IF(COUNTBLANK(I3)=0,I3,"Unknown") -> Rent | S3: =IF(COUNTBLANK(M3)=0,M3,0) -> 5000 | T3: =IF(COUNTBLANK(K3)=0,K3,"Cash/UPI") -> UPI
A4: TXN1002 | B4: 45660 | C4: February | D4: Priya Das | E4: 34 | F4: Mumbai | G4: Freelancing | H4: 72000 | I4: Groceries | J4: 6500 | K4: Card | L4: 15000 | N4: 788 | O4: Good | P4: =IF(COUNTBLANK(F4)=0,F4,"Unknown") -> Mumbai | Q4: =IF(COUNTBLANK(G4)=0,G4,"Unknown") -> Freelancing | R4: =IF(COUNTBLANK(I4)=0,I4,"Unknown") -> Groceries | S4: =IF(COUNTBLANK(M4)=0,M4,0) -> 0 | T4: =IF(COUNTBLANK(K4)=0,K4,"Cash/UPI") -> Card
A5: TXN1003 | B5: 45661 | C5: March | D5: Ankit Roy | E5: 26 | G5: Salary | H5: 54000 | J5: 3200 | K5: Cash | L5: 8000 | M5: 2500 | N5: 689 | O5: Average | P5: =IF(COUNTBLANK(F5)=0,F5,"Unknown") -> Unknown | Q5: =IF(COUNTBLANK(G5)=0,G5,"Unknown") -> Salary | R5: =IF(COUNTBLANK(I5)=0,I5,"Unknown") -> Unknown | S5: =IF(COUNTBLANK(M5)=0,M5,0) -> 2500 | T5: =IF(COUNTBLANK(K5)=0,K5,"Cash/UPI") -> Cash
A6: TXN1004 | B6: 45662 | C6: April | D6: Sneha Paul | E6: 31 | F6: Bangalore | G6: Business | H6: 98000 | I6: Utilities | J6: 5400 | K6: NetBanking | L6: 25000 | M6: 8000 | N6: 801 | O6: Excellent | P6: =IF(COUNTBLANK(F6)=0,F6,"Unknown") -> Bangalore | Q6: =IF(COUNTBLANK(G6)=0,G6,"Unknown") -> Business | R6: =IF(COUNTBLANK(I6)=0,I6,"Unknown") -> Utilities | S6: =IF(COUNTBLANK(M6)=0,M6,0) -> 8000 | T6: =IF(COUNTBLANK(K6)=0,K6,"Cash/UPI") -> NetBanking
A7: TXN1005 | B7: 45663 | C7: May | D7: Rohan Mitra | E7: 38 | F7: Hyderabad | G7: Salary | H7: 85000 | I7: Entertainment | J7: 7600 | K7: Card | L7: 10000 | M7: 12000 | N7: 655 | O7: Risky | P7: =IF(COUNTBLANK(F7)=0,F7,"Unknown") -> Hyderabad | Q7: =IF(COUNTBLANK(G7)=0,G7,"Unknown") -> Salary | R7: =IF(COUNTBLANK(I7)=0,I7,"Unknown") -> Entertainment | S7: =IF(COUNTBLANK(M7)=0,M7,0) -> 12000 | T7: =IF(COUNTBLANK(K7)=0,K7,"Cash/UPI") -> Card
A8: TXN1006 | B8: 45664 | C8: June | D8: Aditi Sharma | E8: 27 | F8: Pune | G8: =IF(COUNTBLANK(G3)=0,G3,"UKNOWN") -> Salary | H8: 61000 | I8: Healthcare | J8: 2400 | K8: UPI | L8: 17000 | N8: 771 | O8: Good | P8: =IF(COUNTBLANK(F8)=0,F8,"Unknown") -> Pune | Q8: =IF(COUNTBLANK(G8)=0,G8,"Unknown") -> Salary | R8: =IF(COUNTBLANK(I8)=0,I8,"Unknown") -> Healthcare | S8: =IF(COUNTBLANK(M8)=0,M8,0) -> 0 | T8: =IF(COUNTBLANK(K8)=0,K8,"Cash/UPI") -> UPI
A9: TXN1007 | B9: 45665 | C9: July | D9: Karan Singh | E9: 42 | F9: Chennai | G9: Business | H9: 120000 | I9: Rent | J9: 25000 | K9: Cheque | L9: 35000 | M9: 18000 | N9: 720 | O9: Stable | P9: =IF(COUNTBLANK(F9)=0,F9,"Unknown") -> Chennai | Q9: =IF(COUNTBLANK(G9)=0,G9,"Unknown") -> Business | R9: =IF(COUNTBLANK(I9)=0,I9,"Unknown") -> Rent | S9: =IF(COUNTBLANK(M9)=0,M9,0) -> 18000 | T9: =IF(COUNTBLANK(K9)=0,K9,"Cash/UPI") -> Cheque
A10: TXN1008 | B10: 45666 | C10: August | D10: Megha Dutta | E10: 24 | F10: Kolkata | G10: Internship | H10: 28000 | I10: Education | J10: 4500 | K10: UPI | L10: 5000 | N10: 690 | O10: Average | P10: =IF(COUNTBLANK(F10)=0,F10,"Unknown") -> Kolkata | Q10: =IF(COUNTBLANK(G10)=0,G10,"Unknown") -> Internship | R10: =IF(COUNTBLANK(I10)=0,I10,"Unknown") -> Education | S10: =IF(COUNTBLANK(M10)=0,M10,0) -> 0 | T10: =IF(COUNTBLANK(K10)=0,K10,"Cash/UPI") -> UPI
A11: TXN1009 | B11: 45667 | C11: September | D11: Arjun Nair | E11: 36 | F11: Kochi | G11: Salary | H11: 76000 | J11: 8200 | K11: Card | L11: 14000 | M11: 7000 | N11: 745 | O11: Stable | P11: =IF(COUNTBLANK(F11)=0,F11,"Unknown") -> Kochi | Q11: =IF(COUNTBLANK(G11)=0,G11,"Unknown") -> Salary | R11: =IF(COUNTBLANK(I11)=0,I11,"Unknown") -> Unknown | S11: =IF(COUNTBLANK(M11)=0,M11,0) -> 7000 | T11: =IF(COUNTBLANK(K11)=0,K11,"Cash/UPI") -> Card
A12: TXN1010 | B12: 45668 | C12: October | D12: Neha Kapoor | E12: 30 | F12: Jaipur | G12: Freelancing | H12: 68000 | I12: Shopping | J12: 9200 | K12: UPI | L12: 11000 | M12: 3000 | N12: 732 | O12: Good | P12: =IF(COUNTBLANK(F12)=0,F12,"Unknown") -> Jaipur | Q12: =IF(COUNTBLANK(G12)=0,G12,"Unknown") -> Freelancing | R12: =IF(COUNTBLANK(I12)=0,I12,"Unknown") -> Shopping | S12: =IF(COUNTBLANK(M12)=0,M12,0) -> 3000 | T12: =IF(COUNTBLANK(K12)=0,K12,"Cash/UPI") -> UPI
A13: TXN1011 | B13: 45669 | C13: November | D13: Vikram Bose | E13: 45 | F13: Kolkata | G13: Business | H13: 150000 | I13: Investment | J13: 35000 | K13: NetBanking | L13: 40000 | M13: 20000 | N13: 810 | O13: Excellent | P13: =IF(COUNTBLANK(F13)=0,F13,"Unknown") -> Kolkata | Q13: =IF(COUNTBLANK(G13)=0,G13,"Unknown") -> Business | R13: =IF(COUNTBLANK(I13)=0,I13,"Unknown") -> Investment | S13: =IF(COUNTBLANK(M13)=0,M13,0) -> 20000 | T13: =IF(COUNTBLANK(K13)=0,K13,"Cash/UPI") -> NetBanking
A14: TXN1012 | B14: 45670 | C14: December | D14: Isha Jain | E14: 28 | F14: Delhi | H14: 59000 | I14: Food | J14: 5800 | L14: 9000 | M14: 2500 | N14: 704 | O14: Stable | P14: =IF(COUNTBLANK(F14)=0,F14,"Unknown") -> Delhi | Q14: =IF(COUNTBLANK(G14)=0,G14,"Unknown") -> Unknown | R14: =IF(COUNTBLANK(I14)=0,I14,"Unknown") -> Food | S14: =IF(COUNTBLANK(M14)=0,M14,0) -> 2500 | T14: =IF(COUNTBLANK(K14)=0,K14,"Cash/UPI") -> Cash/UPI
A15: TXN1013 | B15: 45671 | C15: January | D15: Sourav Ghosh | E15: 33 | G15: Salary | H15: 71000 | I15: Rent | J15: 21000 | K15: UPI | L15: 13000 | M15: 6000 | N15: 740 | O15: Good | P15: =IF(COUNTBLANK(F15)=0,F15,"Unknown") -> Unknown | Q15: =IF(COUNTBLANK(G15)=0,G15,"Unknown") -> Salary | R15: =IF(COUNTBLANK(I15)=0,I15,"Unknown") -> Rent | S15: =IF(COUNTBLANK(M15)=0,M15,0) -> 6000 | T15: =IF(COUNTBLANK(K15)=0,K15,"Cash/UPI") -> UPI
A16: TXN1014 | B16: 45672 | C16: February | D16: Ritika Sen | E16: 25 | F16: Pune | G16: Freelancing | H16: 47000 | I16: Entertainment | J16: 4200 | K16: Card | L16: 7000 | N16: 681 | O16: Average | P16: =IF(COUNTBLANK(F16)=0,F16,"Unknown") -> Pune | Q16: =IF(COUNTBLANK(G16)=0,G16,"Unknown") -> Freelancing | R16: =IF(COUNTBLANK(I16)=0,I16,"Unknown") -> Entertainment | S16: =IF(COUNTBLANK(M16)=0,M16,0) -> 0 | T16: =IF(COUNTBLANK(K16)=0,K16,"Cash/UPI") -> Card
A17: TXN1015 | B17: 45673 | C17: March | D17: Abhishek Das | E17: 39 | F17: Bangalore | G17: Business | H17: 132000 | I17: Healthcare | J17: 6800 | K17: NetBanking | L17: 30000 | M17: 15000 | N17: 790 | O17: Excellent | P17: =IF(COUNTBLANK(F17)=0,F17,"Unknown") -> Bangalore | Q17: =IF(COUNTBLANK(G17)=0,G17,"Unknown") -> Business | R17: =IF(COUNTBLANK(I17)=0,I17,"Unknown") -> Healthcare | S17: =IF(COUNTBLANK(M17)=0,M17,0) -> 15000 | T17: =IF(COUNTBLANK(K17)=0,K17,"Cash/UPI") -> NetBanking
A18: TXN1016 | B18: 45674 | C18: April | D18: Nikita Roy | E18: 29 | F18: Delhi | G18: Salary | H18: 62000 | I18: Groceries | J18: 5900 | K18: UPI | L18: 12000 | M18: 3000 | N18: 725 | O18: Good | P18: =IF(COUNTBLANK(F18)=0,F18,"Unknown") -> Delhi | Q18: =IF(COUNTBLANK(G18)=0,G18,"Unknown") -> Salary | R18: =IF(COUNTBLANK(I18)=0,I18,"Unknown") -> Groceries | S18: =IF(COUNTBLANK(M18)=0,M18,0) -> 3000 | T18: =IF(COUNTBLANK(K18)=0,K18,"Cash/UPI") -> UPI
A19: TXN1017 | B19: 45675 | C19: May | D19: Manish Yadav | E19: 35 | F19: Mumbai | G19: Salary | H19: 81000 | I19: Transport | J19: 4100 | K19: Cash | L19: 16000 | M19: 9000 | N19: 710 | O19: Stable | P19: =IF(COUNTBLANK(F19)=0,F19,"Unknown") -> Mumbai | Q19: =IF(COUNTBLANK(G19)=0,G19,"Unknown") -> Salary | R19: =IF(COUNTBLANK(I19)=0,I19,"Unknown") -> Transport | S19: =IF(COUNTBLANK(M19)=0,M19,0) -> 9000 | T19: =IF(COUNTBLANK(K19)=0,K19,"Cash/UPI") -> Cash
A20: TXN1018 | B20: 45676 | C20: June | D20: Simran Kaur | E20: 27 | F20: Chandigarh | G20: Freelancing | H20: 56000 | J20: 9700 | K20: Card | L20: 8500 | N20: 699 | O20: Average | P20: =IF(COUNTBLANK(F20)=0,F20,"Unknown") -> Chandigarh | Q20: =IF(COUNTBLANK(G20)=0,G20,"Unknown") -> Freelancing | R20: =IF(COUNTBLANK(I20)=0,I20,"Unknown") -> Unknown | S20: =IF(COUNTBLANK(M20)=0,M20,0) -> 0 | T20: =IF(COUNTBLANK(K20)=0,K20,"Cash/UPI") -> Card
A21: TXN1019 | B21: 45677 | C21: July | D21: Raj Malhotra | E21: 41 | F21: Delhi | G21: Business | H21: 145000 | I21: Utilities | J21: 7800 | K21: Cheque | L21: 42000 | M21: 25000 | N21: 805 | O21: Excellent | P21: =IF(COUNTBLANK(F21)=0,F21,"Unknown") -> Delhi | Q21: =IF(COUNTBLANK(G21)=0,G21,"Unknown") -> Business | R21: =IF(COUNTBLANK(I21)=0,I21,"Unknown") -> Utilities | S21: =IF(COUNTBLANK(M21)=0,M21,0) -> 25000 | T21: =IF(COUNTBLANK(K21)=0,K21,"Cash/UPI") -> Cheque
A22: TXN1020 | B22: 45678 | C22: August | D22: Pooja Mehta | E22: 32 | F22: Ahmedabad | G22: Salary | H22: 69000 | I22: Food | J22: 6300 | K22: UPI | L22: 10000 | M22: 4500 | N22: 730 | O22: Good | P22: =IF(COUNTBLANK(F22)=0,F22,"Unknown") -> Ahmedabad | Q22: =IF(COUNTBLANK(G22)=0,G22,"Unknown") -> Salary | R22: =IF(COUNTBLANK(I22)=0,I22,"Unknown") -> Food | S22: =IF(COUNTBLANK(M22)=0,M22,0) -> 4500 | T22: =IF(COUNTBLANK(K22)=0,K22,"Cash/UPI") -> UPI
A23: TXN1021 | B23: 45679 | C23: September | D23: Deepak Kumar | E23: 37 | F23: Patna | G23: Salary | H23: 57000 | I23: Rent | J23: 16000 | K23: Cash | L23: 6000 | M23: 5500 | N23: 670 | O23: Risky | P23: =IF(COUNTBLANK(F23)=0,F23,"Unknown") -> Patna | Q23: =IF(COUNTBLANK(G23)=0,G23,"Unknown") -> Salary | R23: =IF(COUNTBLANK(I23)=0,I23,"Unknown") -> Rent | S23: =IF(COUNTBLANK(M23)=0,M23,0) -> 5500 | T23: =IF(COUNTBLANK(K23)=0,K23,"Cash/UPI") -> Cash
A24: TXN1022 | B24: 45680 | C24: October | D24: Tanvi Shah | E24: 26 | F24: Surat | G24: Freelancing | H24: 52000 | I24: Shopping | J24: 7600 | K24: Card | L24: 9000 | N24: 715 | O24: Stable | P24: =IF(COUNTBLANK(F24)=0,F24,"Unknown") -> Surat | Q24: =IF(COUNTBLANK(G24)=0,G24,"Unknown") -> Freelancing | R24: =IF(COUNTBLANK(I24)=0,I24,"Unknown") -> Shopping | S24: =IF(COUNTBLANK(M24)=0,M24,0) -> 0 | T24: =IF(COUNTBLANK(K24)=0,K24,"Cash/UPI") -> Card
A25: TXN1023 | B25: 45681 | C25: November | D25: Ritesh Verma | E25: 40 | H25: 125000 | I25: Investment | J25: 28000 | K25: NetBanking | L25: 37000 | M25: 12000 | N25: 798 | O25: Excellent | P25: =IF(COUNTBLANK(F25)=0,F25,"Unknown") -> Unknown | Q25: =IF(COUNTBLANK(G25)=0,G25,"Unknown") -> Unknown | R25: =IF(COUNTBLANK(I25)=0,I25,"Unknown") -> Investment | S25: =IF(COUNTBLANK(M25)=0,M25,0) -> 12000 | T25: =IF(COUNTBLANK(K25)=0,K25,"Cash/UPI") -> NetBanking
A26: TXN1024 | B26: 45682 | C26: December | D26: Ananya Ghosh | E26: 31 | F26: Kolkata | G26: Salary | H26: 74000 | I26: Education | J26: 5300 | K26: UPI | L26: 15000 | M26: 5000 | N26: 750 | O26: Good | P26: =IF(COUNTBLANK(F26)=0,F26,"Unknown") -> Kolkata | Q26: =IF(COUNTBLANK(G26)=0,G26,"Unknown") -> Salary | R26: =IF(COUNTBLANK(I26)=0,I26,"Unknown") -> Education | S26: =IF(COUNTBLANK(M26)=0,M26,0) -> 5000 | T26: =IF(COUNTBLANK(K26)=0,K26,"Cash/UPI") -> UPI
A27: TXN1025 | B27: 45683 | C27: January | D27: Kunal Sharma | E27: 28 | F27: Delhi | G27: Salary | H27: 63000 | J27: 8600 | K27: Card | L27: 11000 | M27: 3500 | N27: 721 | O27: Stable | P27: =IF(COUNTBLANK(F27)=0,F27,"Unknown") -> Delhi | Q27: =IF(COUNTBLANK(G27)=0,G27,"Unknown") -> Salary | R27: =IF(COUNTBLANK(I27)=0,I27,"Unknown") -> Unknown | S27: =IF(COUNTBLANK(M27)=0,M27,0) -> 3500 | T27: =IF(COUNTBLANK(K27)=0,K27,"Cash/UPI") -> Card
A28: TXN1075 | B28: 45733 | C28: February | D28: Amit Bose | E28: 36 | F28: Kolkata | G28: Salary | H28: 81000 | I28: Travel | J28: 9400 | K28: UPI | L28: 17000 | M28: 8500 | N28: 743 | O28: Good | P28: =IF(COUNTBLANK(F28)=0,F28,"Unknown") -> Kolkata | Q28: =IF(COUNTBLANK(G28)=0,G28,"Unknown") -> Salary | R28: =IF(COUNTBLANK(I28)=0,I28,"Unknown") -> Travel | S28: =IF(COUNTBLANK(M28)=0,M28,0) -> 8500 | T28: =IF(COUNTBLANK(K28)=0,K28,"Cash/UPI") -> UPI
A29: TXN1076 | B29: 45734 | C29: March | D29: Sonia Jain | E29: 27 | F29: Pune | G29: Freelancing | H29: 55000 | I29: Food | J29: 5200 | K29: Card | L29: 8000 | N29: 701 | O29: Stable | P29: =IF(COUNTBLANK(F29)=0,F29,"Unknown") -> Pune | Q29: =IF(COUNTBLANK(G29)=0,G29,"Unknown") -> Freelancing | R29: =IF(COUNTBLANK(I29)=0,I29,"Unknown") -> Food | S29: =IF(COUNTBLANK(M29)=0,M29,0) -> 0 | T29: =IF(COUNTBLANK(K29)=0,K29,"Cash/UPI") -> Card
A30: TXN1077 | B30: 45735 | C30: April | D30: Harsh Vardhan | E30: 43 | F30: Delhi | G30: Business | H30: 149000 | I30: Investment | J30: 41000 | K30: Cheque | L30: 50000 | M30: 23000 | N30: 815 | O30: Excellent | P30: =IF(COUNTBLANK(F30)=0,F30,"Unknown") -> Delhi | Q30: =IF(COUNTBLANK(G30)=0,G30,"Unknown") -> Business | R30: =IF(COUNTBLANK(I30)=0,I30,"Unknown") -> Investment | S30: =IF(COUNTBLANK(M30)=0,M30,0) -> 23000 | T30: =IF(COUNTBLANK(K30)=0,K30,"Cash/UPI") -> Cheque
A31: TXN1078 | B31: 45736 | C31: May | D31: Ankita Sen | E31: 30 | F31: Kolkata | G31: Salary | H31: 72000 | I31: Utilities | J31: 6300 | K31: UPI | L31: 14500 | M31: 3500 | N31: 735 | O31: Good | P31: =IF(COUNTBLANK(F31)=0,F31,"Unknown") -> Kolkata | Q31: =IF(COUNTBLANK(G31)=0,G31,"Unknown") -> Salary | R31: =IF(COUNTBLANK(I31)=0,I31,"Unknown") -> Utilities | S31: =IF(COUNTBLANK(M31)=0,M31,0) -> 3500 | T31: =IF(COUNTBLANK(K31)=0,K31,"Cash/UPI") -> UPI
A32: TXN1079 | B32: 45737 | C32: June | D32: Rohan Sharma | E32: 28 | F32: Delhi | G32: Salary | H32: 65000 | I32: Transport | J32: 4800 | K32: Cash | L32: 10000 | M32: 4000 | N32: 712 | O32: Stable | P32: =IF(COUNTBLANK(F32)=0,F32,"Unknown") -> Delhi | Q32: =IF(COUNTBLANK(G32)=0,G32,"Unknown") -> Salary | R32: =IF(COUNTBLANK(I32)=0,I32,"Unknown") -> Transport | S32: =IF(COUNTBLANK(M32)=0,M32,0) -> 4000 | T32: =IF(COUNTBLANK(K32)=0,K32,"Cash/UPI") -> Cash
A33: TXN1080 | B33: 45738 | C33: July | D33: Priya Roy | E33: 25 | F33: Kolkata | G33: Freelancing | H33: 50000 | I33: Shopping | J33: 8100 | K33: Card | L33: 6000 | N33: 689 | O33: Average | P33: =IF(COUNTBLANK(F33)=0,F33,"Unknown") -> Kolkata | Q33: =IF(COUNTBLANK(G33)=0,G33,"Unknown") -> Freelancing | R33: =IF(COUNTBLANK(I33)=0,I33,"Unknown") -> Shopping | S33: =IF(COUNTBLANK(M33)=0,M33,0) -> 0 | T33: =IF(COUNTBLANK(K33)=0,K33,"Cash/UPI") -> Card
A34: TXN1081 | B34: 45739 | C34: August | D34: Abhishek Jain | E34: 40 | F34: Mumbai | H34: 137000 | I34: Rent | J34: 33000 | L34: 41000 | M34: 17000 | N34: 799 | O34: Excellent | P34: =IF(COUNTBLANK(F34)=0,F34,"Unknown") -> Mumbai | Q34: =IF(COUNTBLANK(G34)=0,G34,"Unknown") -> Unknown | R34: =IF(COUNTBLANK(I34)=0,I34,"Unknown") -> Rent | S34: =IF(COUNTBLANK(M34)=0,M34,0) -> 17000 | T34: =IF(COUNTBLANK(K34)=0,K34,"Cash/UPI") -> Cash/UPI
A35: TXN1082 | B35: 45740 | C35: September | D35: Tania Das | E35: 31 | F35: Kolkata | G35: Salary | H35: 70000 | I35: Healthcare | J35: 4600 | K35: UPI | L35: 13000 | M35: 3000 | N35: 732 | O35: Good | P35: =IF(COUNTBLANK(F35)=0,F35,"Unknown") -> Kolkata | Q35: =IF(COUNTBLANK(G35)=0,G35,"Unknown") -> Salary | R35: =IF(COUNTBLANK(I35)=0,I35,"Unknown") -> Healthcare | S35: =IF(COUNTBLANK(M35)=0,M35,0) -> 3000 | T35: =IF(COUNTBLANK(K35)=0,K35,"Cash/UPI") -> UPI
A36: TXN1083 | B36: 45741 | C36: October | D36: Manish Roy | E36: 35 | F36: Delhi | G36: Salary | H36: 83000 | I36: Travel | J36: 10200 | K36: Card | L36: 18000 | M36: 9500 | N36: 747 | O36: Good | P36: =IF(COUNTBLANK(F36)=0,F36,"Unknown") -> Delhi | Q36: =IF(COUNTBLANK(G36)=0,G36,"Unknown") -> Salary | R36: =IF(COUNTBLANK(I36)=0,I36,"Unknown") -> Travel | S36: =IF(COUNTBLANK(M36)=0,M36,0) -> 9500 | T36: =IF(COUNTBLANK(K36)=0,K36,"Cash/UPI") -> Card
A37: TXN1084 | B37: 45742 | C37: November | D37: Sweta Kapoor | E37: 26 | F37: Pune | G37: Freelancing | H37: 53000 | I37: Entertainment | J37: 4100 | K37: Cash | L37: 7000 | N37: 694 | O37: Average | P37: =IF(COUNTBLANK(F37)=0,F37,"Unknown") -> Pune | Q37: =IF(COUNTBLANK(G37)=0,G37,"Unknown") -> Freelancing | R37: =IF(COUNTBLANK(I37)=0,I37,"Unknown") -> Entertainment | S37: =IF(COUNTBLANK(M37)=0,M37,0) -> 0 | T37: =IF(COUNTBLANK(K37)=0,K37,"Cash/UPI") -> Cash
A38: TXN1085 | B38: 45743 | C38: December | D38: Kunal Verma | E38: 42 | F38: Ahmedabad | G38: Business | H38: 144000 | I38: Investment | J38: 37000 | K38: Cheque | L38: 46000 | M38: 21000 | N38: 810 | O38: Excellent | P38: =IF(COUNTBLANK(F38)=0,F38,"Unknown") -> Ahmedabad | Q38: =IF(COUNTBLANK(G38)=0,G38,"Unknown") -> Business | R38: =IF(COUNTBLANK(I38)=0,I38,"Unknown") -> Investment | S38: =IF(COUNTBLANK(M38)=0,M38,0) -> 21000 | T38: =IF(COUNTBLANK(K38)=0,K38,"Cash/UPI") -> Cheque
A39: TXN1086 | B39: 45744 | C39: January | D39: Megha Roy | E39: 29 | F39: Kolkata | G39: Salary | H39: 69000 | I39: Groceries | J39: 6200 | K39: UPI | L39: 12500 | M39: 3000 | N39: 728 | O39: Good | P39: =IF(COUNTBLANK(F39)=0,F39,"Unknown") -> Kolkata | Q39: =IF(COUNTBLANK(G39)=0,G39,"Unknown") -> Salary | R39: =IF(COUNTBLANK(I39)=0,I39,"Unknown") -> Groceries | S39: =IF(COUNTBLANK(M39)=0,M39,0) -> 3000 | T39: =IF(COUNTBLANK(K39)=0,K39,"Cash/UPI") -> UPI
A40: TXN1087 | B40: 45745 | C40: February | D40: Rajat Das | E40: 33 | G40: Salary | H40: 78000 | I40: Rent | J40: 22000 | K40: Card | L40: 15000 | M40: 7000 | N40: 739 | O40: Good | P40: =IF(COUNTBLANK(F40)=0,F40,"Unknown") -> Unknown | Q40: =IF(COUNTBLANK(G40)=0,G40,"Unknown") -> Salary | R40: =IF(COUNTBLANK(I40)=0,I40,"Unknown") -> Rent | S40: =IF(COUNTBLANK(M40)=0,M40,0) -> 7000 | T40: =IF(COUNTBLANK(K40)=0,K40,"Cash/UPI") -> Card
A41: TXN1088 | B41: 45746 | C41: March | D41: Sneha Kapoor | E41: 24 | F41: Kolkata | G41: Internship | H41: 30000 | I41: Food | J41: 3500 | K41: Cash | L41: 4000 | N41: 680 | O41: Average | P41: =IF(COUNTBLANK(F41)=0,F41,"Unknown") -> Kolkata | Q41: =IF(COUNTBLANK(G41)=0,G41,"Unknown") -> Internship | R41: =IF(COUNTBLANK(I41)=0,I41,"Unknown") -> Food | S41: =IF(COUNTBLANK(M41)=0,M41,0) -> 0 | T41: =IF(COUNTBLANK(K41)=0,K41,"Cash/UPI") -> Cash
A42: TXN1089 | B42: 45747 | C42: April | D42: Arvind Sharma | E42: 45 | F42: Bangalore | G42: Business | H42: 158000 | I42: Healthcare | J42: 9100 | K42: NetBanking | L42: 54000 | M42: 8000 | N42: 822 | O42: Excellent | P42: =IF(COUNTBLANK(F42)=0,F42,"Unknown") -> Bangalore | Q42: =IF(COUNTBLANK(G42)=0,G42,"Unknown") -> Business | R42: =IF(COUNTBLANK(I42)=0,I42,"Unknown") -> Healthcare | S42: =IF(COUNTBLANK(M42)=0,M42,0) -> 8000 | T42: =IF(COUNTBLANK(K42)=0,K42,"Cash/UPI") -> NetBanking
A43: TXN1090 | B43: 45748 | C43: May | D43: Neha Das | E43: 30 | F43: Kolkata | H43: 73000 | I43: Shopping | J43: 7900 | L43: 13500 | M43: 4000 | N43: 736 | O43: Good | P43: =IF(COUNTBLANK(F43)=0,F43,"Unknown") -> Kolkata | Q43: =IF(COUNTBLANK(G43)=0,G43,"Unknown") -> Unknown | R43: =IF(COUNTBLANK(I43)=0,I43,"Unknown") -> Shopping | S43: =IF(COUNTBLANK(M43)=0,M43,0) -> 4000 | T43: =IF(COUNTBLANK(K43)=0,K43,"Cash/UPI") -> Cash/UPI
A44: TXN1091 | B44: 45749 | C44: June | D44: Rahul Mehta | E44: 36 | F44: Mumbai | G44: Salary | H44: 86000 | J44: 9700 | K44: Card | L44: 19000 | M44: 10000 | N44: 748 | O44: Good | P44: =IF(COUNTBLANK(F44)=0,F44,"Unknown") -> Mumbai | Q44: =IF(COUNTBLANK(G44)=0,G44,"Unknown") -> Salary | R44: =IF(COUNTBLANK(I44)=0,I44,"Unknown") -> Unknown | S44: =IF(COUNTBLANK(M44)=0,M44,0) -> 10000 | T44: =IF(COUNTBLANK(K44)=0,K44,"Cash/UPI") -> Card
A45: TXN1092 | B45: 45750 | C45: July | D45: Priyanka Roy | E45: 27 | F45: Kolkata | G45: Freelancing | H45: 52000 | I45: Entertainment | J45: 4500 | K45: UPI | L45: 6500 | N45: 696 | O45: Average | P45: =IF(COUNTBLANK(F45)=0,F45,"Unknown") -> Kolkata | Q45: =IF(COUNTBLANK(G45)=0,G45,"Unknown") -> Freelancing | R45: =IF(COUNTBLANK(I45)=0,I45,"Unknown") -> Entertainment | S45: =IF(COUNTBLANK(M45)=0,M45,0) -> 0 | T45: =IF(COUNTBLANK(K45)=0,K45,"Cash/UPI") -> UPI
A46: TXN1093 | B46: 45751 | C46: August | D46: Vikas Jain | E46: 41 | F46: Delhi | G46: Business | H46: 139000 | I46: Investment | J46: 35000 | K46: Cheque | L46: 42000 | M46: 18000 | N46: 801 | O46: Excellent | P46: =IF(COUNTBLANK(F46)=0,F46,"Unknown") -> Delhi | Q46: =IF(COUNTBLANK(G46)=0,G46,"Unknown") -> Business | R46: =IF(COUNTBLANK(I46)=0,I46,"Unknown") -> Investment | S46: =IF(COUNTBLANK(M46)=0,M46,0) -> 18000 | T46: =IF(COUNTBLANK(K46)=0,K46,"Cash/UPI") -> Cheque
A47: TXN1094 | B47: 45752 | C47: September | D47: Sohini Sen | E47: 31 | F47: Kolkata | G47: Salary | H47: 71000 | I47: Utilities | J47: 6100 | K47: Card | L47: 14000 | M47: 3500 | N47: 734 | O47: Good | P47: =IF(COUNTBLANK(F47)=0,F47,"Unknown") -> Kolkata | Q47: =IF(COUNTBLANK(G47)=0,G47,"Unknown") -> Salary | R47: =IF(COUNTBLANK(I47)=0,I47,"Unknown") -> Utilities | S47: =IF(COUNTBLANK(M47)=0,M47,0) -> 3500 | T47: =IF(COUNTBLANK(K47)=0,K47,"Cash/UPI") -> Card
A48: TXN1095 | B48: 45753 | C48: October | D48: Ankit Sharma | E48: 28 | G48: Salary | H48: 67000 | I48: Rent | J48: 19500 | K48: UPI | L48: 10500 | M48: 4500 | N48: 718 | O48: Stable | P48: =IF(COUNTBLANK(F48)=0,F48,"Unknown") -> Unknown | Q48: =IF(COUNTBLANK(G48)=0,G48,"Unknown") -> Salary | R48: =IF(COUNTBLANK(I48)=0,I48,"Unknown") -> Rent | S48: =IF(COUNTBLANK(M48)=0,M48,0) -> 4500 | T48: =IF(COUNTBLANK(K48)=0,K48,"Cash/UPI") -> UPI
A49: TXN1096 | B49: 45754 | C49: November | D49: Tina Roy | E49: 25 | F49: Kolkata | G49: Internship | H49: 31000 | I49: Education | J49: 3900 | K49: Cash | L49: 3000 | N49: 677 | O49: Average | P49: =IF(COUNTBLANK(F49)=0,F49,"Unknown") -> Kolkata | Q49: =IF(COUNTBLANK(G49)=0,G49,"Unknown") -> Internship | R49: =IF(COUNTBLANK(I49)=0,I49,"Unknown") -> Education | S49: =IF(COUNTBLANK(M49)=0,M49,0) -> 0 | T49: =IF(COUNTBLANK(K49)=0,K49,"Cash/UPI") -> Cash
A50: TXN1097 | B50: 45755 | C50: December | D50: Rakesh Gupta | E50: 43 | F50: Ahmedabad | G50: Business | H50: 148000 | I50: Healthcare | J50: 8300 | K50: NetBanking | L50: 49000 | M50: 22000 | N50: 814 | O50: Excellent | P50: =IF(COUNTBLANK(F50)=0,F50,"Unknown") -> Ahmedabad | Q50: =IF(COUNTBLANK(G50)=0,G50,"Unknown") -> Business | R50: =IF(COUNTBLANK(I50)=0,I50,"Unknown") -> Healthcare | S50: =IF(COUNTBLANK(M50)=0,M50,0) -> 22000 | T50: =IF(COUNTBLANK(K50)=0,K50,"Cash/UPI") -> NetBanking
A51: TXN1098 | B51: 45756 | C51: January | D51: Pallabi Das | E51: 30 | F51: Kolkata | G51: Salary | H51: 72000 | I51: Shopping | J51: 7400 | K51: UPI | L51: 13200 | M51: 3000 | N51: 731 | O51: Good | P51: =IF(COUNTBLANK(F51)=0,F51,"Unknown") -> Kolkata | Q51: =IF(COUNTBLANK(G51)=0,G51,"Unknown") -> Salary | R51: =IF(COUNTBLANK(I51)=0,I51,"Unknown") -> Shopping | S51: =IF(COUNTBLANK(M51)=0,M51,0) -> 3000 | T51: =IF(COUNTBLANK(K51)=0,K51,"Cash/UPI") -> UPI
A52: TXN1099 | B52: 45757 | C52: February | D52: Sumit Roy | E52: 35 | F52: Delhi | H52: 80000 | I52: Travel | J52: 10100 | K52: Card | L52: 17500 | M52: 9000 | N52: 744 | O52: Good | P52: =IF(COUNTBLANK(F52)=0,F52,"Unknown") -> Delhi | Q52: =IF(COUNTBLANK(G52)=0,G52,"Unknown") -> Unknown | R52: =IF(COUNTBLANK(I52)=0,I52,"Unknown") -> Travel | S52: =IF(COUNTBLANK(M52)=0,M52,0) -> 9000 | T52: =IF(COUNTBLANK(K52)=0,K52,"Cash/UPI") -> Card
A53: TXN1100 | B53: 45758 | C53: March | D53: Ayesha Khan | E53: 27 | F53: Kolkata | G53: Freelancing | H53: 54000 | I53: Food | J53: 5100 | K53: UPI | L53: 7200 | N53: 700 | O53: Stable | P53: =IF(COUNTBLANK(F53)=0,F53,"Unknown") -> Kolkata | Q53: =IF(COUNTBLANK(G53)=0,G53,"Unknown") -> Freelancing | R53: =IF(COUNTBLANK(I53)=0,I53,"Unknown") -> Food | S53: =IF(COUNTBLANK(M53)=0,M53,0) -> 0 | T53: =IF(COUNTBLANK(K53)=0,K53,"Cash/UPI") -> UPI
A54: TXN1026 | B54: 45684 | C54: April | D54: Shreya Banerjee | E54: 30 | F54: Kolkata | G54: Salary | H54: 67000 | I54: Healthcare | J54: 3400 | K54: UPI | L54: 14000 | M54: 2500 | N54: 738 | O54: Good | P54: =IF(COUNTBLANK(F54)=0,F54,"Unknown") -> Kolkata | Q54: =IF(COUNTBLANK(G54)=0,G54,"Unknown") -> Salary | R54: =IF(COUNTBLANK(I54)=0,I54,"Unknown") -> Healthcare | S54: =IF(COUNTBLANK(M54)=0,M54,0) -> 2500 | T54: =IF(COUNTBLANK(K54)=0,K54,"Cash/UPI") -> UPI
A55: TXN1027 | B55: 45685 | C55: May | D55: Aman Verma | E55: 27 | F55: Delhi | G55: Freelancing | H55: 51000 | J55: 4700 | K55: Cash | L55: 6000 | N55: 688 | O55: Average | P55: =IF(COUNTBLANK(F55)=0,F55,"Unknown") -> Delhi | Q55: =IF(COUNTBLANK(G55)=0,G55,"Unknown") -> Freelancing | R55: =IF(COUNTBLANK(I55)=0,I55,"Unknown") -> Unknown | S55: =IF(COUNTBLANK(M55)=0,M55,0) -> 0 | T55: =IF(COUNTBLANK(K55)=0,K55,"Cash/UPI") -> Cash
A56: TXN1028 | B56: 45686 | C56: June | D56: Niharika Bose | E56: 35 | F56: Bangalore | G56: Business | H56: 118000 | I56: Rent | J56: 28000 | L56: 32000 | M56: 14000 | N56: 799 | O56: Excellent | P56: =IF(COUNTBLANK(F56)=0,F56,"Unknown") -> Bangalore | Q56: =IF(COUNTBLANK(G56)=0,G56,"Unknown") -> Business | R56: =IF(COUNTBLANK(I56)=0,I56,"Unknown") -> Rent | S56: =IF(COUNTBLANK(M56)=0,M56,0) -> 14000 | T56: =IF(COUNTBLANK(K56)=0,K56,"Cash/UPI") -> Cash/UPI
A57: TXN1029 | B57: 45687 | C57: July | D57: Rajeev Kumar | E57: 44 | G57: Salary | H57: 83000 | I57: Utilities | J57: 7200 | K57: NetBanking | L57: 18000 | M57: 10000 | N57: 712 | O57: Stable | P57: =IF(COUNTBLANK(F57)=0,F57,"Unknown") -> Unknown | Q57: =IF(COUNTBLANK(G57)=0,G57,"Unknown") -> Salary | R57: =IF(COUNTBLANK(I57)=0,I57,"Unknown") -> Utilities | S57: =IF(COUNTBLANK(M57)=0,M57,0) -> 10000 | T57: =IF(COUNTBLANK(K57)=0,K57,"Cash/UPI") -> NetBanking
A58: TXN1030 | B58: 45688 | C58: August | D58: Anjali Roy | E58: 26 | F58: Kolkata | G58: Internship | H58: 31000 | I58: Education | J58: 3800 | K58: UPI | L58: 4500 | N58: 675 | O58: Average | P58: =IF(COUNTBLANK(F58)=0,F58,"Unknown") -> Kolkata | Q58: =IF(COUNTBLANK(G58)=0,G58,"Unknown") -> Internship | R58: =IF(COUNTBLANK(I58)=0,I58,"Unknown") -> Education | S58: =IF(COUNTBLANK(M58)=0,M58,0) -> 0 | T58: =IF(COUNTBLANK(K58)=0,K58,"Cash/UPI") -> UPI
A59: TXN1031 | B59: 45689 | C59: September | D59: Sahil Mehta | E59: 33 | F59: Mumbai | G59: Salary | H59: 78000 | I59: Travel | J59: 9100 | K59: Card | L59: 13000 | M59: 5000 | N59: 741 | O59: Good | P59: =IF(COUNTBLANK(F59)=0,F59,"Unknown") -> Mumbai | Q59: =IF(COUNTBLANK(G59)=0,G59,"Unknown") -> Salary | R59: =IF(COUNTBLANK(I59)=0,I59,"Unknown") -> Travel | S59: =IF(COUNTBLANK(M59)=0,M59,0) -> 5000 | T59: =IF(COUNTBLANK(K59)=0,K59,"Cash/UPI") -> Card
A60: TXN1032 | B60: 45690 | C60: October | D60: Ritu Sharma | E60: 29 | F60: Jaipur | G60: Freelancing | H60: 56000 | I60: Shopping | J60: 6900 | K60: UPI | L60: 8000 | M60: 7000 | N60: 701 | O60: Stable | P60: =IF(COUNTBLANK(F60)=0,F60,"Unknown") -> Jaipur | Q60: =IF(COUNTBLANK(G60)=0,G60,"Unknown") -> Freelancing | R60: =IF(COUNTBLANK(I60)=0,I60,"Unknown") -> Shopping | S60: =IF(COUNTBLANK(M60)=0,M60,0) -> 7000 | T60: =IF(COUNTBLANK(K60)=0,K60,"Cash/UPI") -> UPI
A61: TXN1033 | B61: 45691 | C61: November | D61: Vivek Singh | E61: 39 | F61: Delhi | H61: 138000 | I61: Investment | J61: 32000 | K61: NetBanking | L61: 41000 | M61: 18000 | N61: 807 | O61: Excellent | P61: =IF(COUNTBLANK(F61)=0,F61,"Unknown") -> Delhi | Q61: =IF(COUNTBLANK(G61)=0,G61,"Unknown") -> Unknown | R61: =IF(COUNTBLANK(I61)=0,I61,"Unknown") -> Investment | S61: =IF(COUNTBLANK(M61)=0,M61,0) -> 18000 | T61: =IF(COUNTBLANK(K61)=0,K61,"Cash/UPI") -> NetBanking
A62: TXN1034 | B62: 45692 | C62: December | D62: Pallavi Das | E62: 31 | F62: Kolkata | G62: Salary | H62: 69000 | I62: Groceries | J62: 6400 | K62: Card | L62: 12000 | M62: 3000 | N62: 728 | O62: Good | P62: =IF(COUNTBLANK(F62)=0,F62,"Unknown") -> Kolkata | Q62: =IF(COUNTBLANK(G62)=0,G62,"Unknown") -> Salary | R62: =IF(COUNTBLANK(I62)=0,I62,"Unknown") -> Groceries | S62: =IF(COUNTBLANK(M62)=0,M62,0) -> 3000 | T62: =IF(COUNTBLANK(K62)=0,K62,"Cash/UPI") -> Card
A63: TXN1035 | B63: 45693 | C63: January | D63: Arindam Sen | E63: 28 | F63: Kolkata | G63: Salary | H63: 62000 | I63: Rent | J63: 19000 | K63: UPI | L63: 10000 | M63: 4000 | N63: 719 | O63: Stable | P63: =IF(COUNTBLANK(F63)=0,F63,"Unknown") -> Kolkata | Q63: =IF(COUNTBLANK(G63)=0,G63,"Unknown") -> Salary | R63: =IF(COUNTBLANK(I63)=0,I63,"Unknown") -> Rent | S63: =IF(COUNTBLANK(M63)=0,M63,0) -> 4000 | T63: =IF(COUNTBLANK(K63)=0,K63,"Cash/UPI") -> UPI
A64: TXN1036 | B64: 45694 | C64: February | D64: Neeraj Kapoor | E64: 36 | F64: Delhi | G64: Salary | H64: 87000 | I64: Transport | J64: 4300 | K64: Cash | L64: 17000 | M64: 8500 | N64: 734 | O64: Good | P64: =IF(COUNTBLANK(F64)=0,F64,"Unknown") -> Delhi | Q64: =IF(COUNTBLANK(G64)=0,G64,"Unknown") -> Salary | R64: =IF(COUNTBLANK(I64)=0,I64,"Unknown") -> Transport | S64: =IF(COUNTBLANK(M64)=0,M64,0) -> 8500 | T64: =IF(COUNTBLANK(K64)=0,K64,"Cash/UPI") -> Cash
A65: TXN1037 | B65: 45695 | C65: March | D65: Komal Jain | E65: 24 | F65: Pune | G65: Internship | H65: 29000 | I65: Entertainment | J65: 3600 | K65: UPI | L65: 3000 | N65: 682 | O65: Average | P65: =IF(COUNTBLANK(F65)=0,F65,"Unknown") -> Pune | Q65: =IF(COUNTBLANK(G65)=0,G65,"Unknown") -> Internship | R65: =IF(COUNTBLANK(I65)=0,I65,"Unknown") -> Entertainment | S65: =IF(COUNTBLANK(M65)=0,M65,0) -> 0 | T65: =IF(COUNTBLANK(K65)=0,K65,"Cash/UPI") -> UPI
A66: TXN1038 | B66: 45696 | C66: April | D66: Harsh Patel | E66: 41 | F66: Ahmedabad | G66: Business | H66: 128000 | I66: Healthcare | J66: 7600 | K66: Cheque | L66: 35000 | M66: 16000 | N66: 792 | O66: Excellent | P66: =IF(COUNTBLANK(F66)=0,F66,"Unknown") -> Ahmedabad | Q66: =IF(COUNTBLANK(G66)=0,G66,"Unknown") -> Business | R66: =IF(COUNTBLANK(I66)=0,I66,"Unknown") -> Healthcare | S66: =IF(COUNTBLANK(M66)=0,M66,0) -> 16000 | T66: =IF(COUNTBLANK(K66)=0,K66,"Cash/UPI") -> Cheque
A67: TXN1039 | B67: 45697 | C67: May | D67: Sonia Gupta | E67: 32 | G67: Salary | H67: 71000 | J67: 6100 | K67: Card | L67: 11000 | M67: 4500 | N67: 725 | O67: Good | P67: =IF(COUNTBLANK(F67)=0,F67,"Unknown") -> Unknown | Q67: =IF(COUNTBLANK(G67)=0,G67,"Unknown") -> Salary | R67: =IF(COUNTBLANK(I67)=0,I67,"Unknown") -> Unknown | S67: =IF(COUNTBLANK(M67)=0,M67,0) -> 4500 | T67: =IF(COUNTBLANK(K67)=0,K67,"Cash/UPI") -> Card
A68: TXN1040 | B68: 45698 | C68: June | D68: Rahul Sen | E68: 29 | F68: Kolkatta | G68: Salary | H68: 65000 | I68: Rent | J68: 18000 | K68: UPI | L68: 9000 | M68: 5000 | N68: 742 | O68: Stable | P68: =IF(COUNTBLANK(F68)=0,F68,"Unknown") -> Kolkatta | Q68: =IF(COUNTBLANK(G68)=0,G68,"Unknown") -> Salary | R68: =IF(COUNTBLANK(I68)=0,I68,"Unknown") -> Rent | S68: =IF(COUNTBLANK(M68)=0,M68,0) -> 5000 | T68: =IF(COUNTBLANK(K68)=0,K68,"Cash/UPI") -> UPI
A69: TXN1041 | B69: 45699 | C69: July | D69: Tina Dey | E69: 27 | F69: Kolkata | G69: Freelancing | H69: 53000 | I69: Shopping | J69: 7900 | K69: UPI | L69: 7000 | N69: 695 | O69: Average | P69: =IF(COUNTBLANK(F69)=0,F69,"Unknown") -> Kolkata | Q69: =IF(COUNTBLANK(G69)=0,G69,"Unknown") -> Freelancing | R69: =IF(COUNTBLANK(I69)=0,I69,"Unknown") -> Shopping | S69: =IF(COUNTBLANK(M69)=0,M69,0) -> 0 | T69: =IF(COUNTBLANK(K69)=0,K69,"Cash/UPI") -> UPI
A70: TXN1042 | B70: 45700 | C70: August | D70: Aditya Rao | E70: 38 | F70: Hyderabad | G70: Salary | H70: 92000 | I70: Travel | J70: 10400 | K70: Card | L70: 20000 | M70: 12000 | N70: 755 | O70: Good | P70: =IF(COUNTBLANK(F70)=0,F70,"Unknown") -> Hyderabad | Q70: =IF(COUNTBLANK(G70)=0,G70,"Unknown") -> Salary | R70: =IF(COUNTBLANK(I70)=0,I70,"Unknown") -> Travel | S70: =IF(COUNTBLANK(M70)=0,M70,0) -> 12000 | T70: =IF(COUNTBLANK(K70)=0,K70,"Cash/UPI") -> Card
A71: TXN1043 | B71: 45701 | C71: September | D71: Meenakshi Iyer | E71: 34 | F71: Chennai | G71: Business | H71: 142000 | I71: Investment | J71: 36000 | K71: NetBanking | L71: 45000 | M71: 20000 | N71: 812 | O71: Excellent | P71: =IF(COUNTBLANK(F71)=0,F71,"Unknown") -> Chennai | Q71: =IF(COUNTBLANK(G71)=0,G71,"Unknown") -> Business | R71: =IF(COUNTBLANK(I71)=0,I71,"Unknown") -> Investment | S71: =IF(COUNTBLANK(M71)=0,M71,0) -> 20000 | T71: =IF(COUNTBLANK(K71)=0,K71,"Cash/UPI") -> NetBanking
A72: TXN1044 | B72: 45702 | C72: October | D72: Rakesh Yadav | E72: 43 | F72: Patna | G72: Salary | H72: 61000 | I72: Utilities | J72: 5900 | K72: Cash | L72: 8000 | M72: 7000 | N72: 676 | O72: Risky | P72: =IF(COUNTBLANK(F72)=0,F72,"Unknown") -> Patna | Q72: =IF(COUNTBLANK(G72)=0,G72,"Unknown") -> Salary | R72: =IF(COUNTBLANK(I72)=0,I72,"Unknown") -> Utilities | S72: =IF(COUNTBLANK(M72)=0,M72,0) -> 7000 | T72: =IF(COUNTBLANK(K72)=0,K72,"Cash/UPI") -> Cash
A73: TXN1045 | B73: 45703 | C73: November | D73: Swati Ghosh | E73: 29 | F73: Kolkata | H73: 73000 | I73: Healthcare | J73: 4100 | K73: UPI | L73: 15000 | M73: 3000 | N73: 744 | O73: Good | P73: =IF(COUNTBLANK(F73)=0,F73,"Unknown") -> Kolkata | Q73: =IF(COUNTBLANK(G73)=0,G73,"Unknown") -> Unknown | R73: =IF(COUNTBLANK(I73)=0,I73,"Unknown") -> Healthcare | S73: =IF(COUNTBLANK(M73)=0,M73,0) -> 3000 | T73: =IF(COUNTBLANK(K73)=0,K73,"Cash/UPI") -> UPI
A74: TXN1046 | B74: 45704 | C74: December | D74: Imran Ali | E74: 37 | F74: Mumbai | G74: Freelancing | H74: 64000 | I74: Food | J74: 5600 | K74: Card | L74: 12000 | M74: 2500 | N74: 718 | O74: Stable | P74: =IF(COUNTBLANK(F74)=0,F74,"Unknown") -> Mumbai | Q74: =IF(COUNTBLANK(G74)=0,G74,"Unknown") -> Freelancing | R74: =IF(COUNTBLANK(I74)=0,I74,"Unknown") -> Food | S74: =IF(COUNTBLANK(M74)=0,M74,0) -> 2500 | T74: =IF(COUNTBLANK(K74)=0,K74,"Cash/UPI") -> Card
A75: TXN1047 | B75: 45705 | C75: January | D75: Priyanka Sen | E75: 26 | F75: Delhi | G75: Salary | H75: 58000 | I75: Education | J75: 6200 | K75: UPI | L75: 9000 | M75: 9800 | N75: 708 | O75: Stable | P75: =IF(COUNTBLANK(F75)=0,F75,"Unknown") -> Delhi | Q75: =IF(COUNTBLANK(G75)=0,G75,"Unknown") -> Salary | R75: =IF(COUNTBLANK(I75)=0,I75,"Unknown") -> Education | S75: =IF(COUNTBLANK(M75)=0,M75,0) -> 9800 | T75: =IF(COUNTBLANK(K75)=0,K75,"Cash/UPI") -> UPI
A76: TXN1048 | B76: 45706 | C76: February | D76: Ajay Malhotra | E76: 45 | F76: Bangalore | G76: Business | H76: 155000 | I76: Rent | J76: 34000 | L76: 50000 | M76: 22000 | N76: 820 | O76: Excellent | P76: =IF(COUNTBLANK(F76)=0,F76,"Unknown") -> Bangalore | Q76: =IF(COUNTBLANK(G76)=0,G76,"Unknown") -> Business | R76: =IF(COUNTBLANK(I76)=0,I76,"Unknown") -> Rent | S76: =IF(COUNTBLANK(M76)=0,M76,0) -> 22000 | T76: =IF(COUNTBLANK(K76)=0,K76,"Cash/UPI") -> Cash/UPI
A77: TXN1049 | B77: 45707 | C77: March | D77: Nupur Das | E77: 30 | F77: Kolkata | G77: Salary | H77: 70000 | I77: Entertainment | J77: 5300 | K77: Card | L77: 13000 | M77: 3500 | N77: 731 | O77: Good | P77: =IF(COUNTBLANK(F77)=0,F77,"Unknown") -> Kolkata | Q77: =IF(COUNTBLANK(G77)=0,G77,"Unknown") -> Salary | R77: =IF(COUNTBLANK(I77)=0,I77,"Unknown") -> Entertainment | S77: =IF(COUNTBLANK(M77)=0,M77,0) -> 3500 | T77: =IF(COUNTBLANK(K77)=0,K77,"Cash/UPI") -> Card
A78: TXN1050 | B78: 45708 | C78: April | D78: Karan Oberoi | E78: 35 | F78: Delhi | G78: Salary | H78: 84000 | I78: Transport | J78: 4800 | K78: Cash | L78: 16000 | M78: 9000 | N78: 726 | O78: Stable | P78: =IF(COUNTBLANK(F78)=0,F78,"Unknown") -> Delhi | Q78: =IF(COUNTBLANK(G78)=0,G78,"Unknown") -> Salary | R78: =IF(COUNTBLANK(I78)=0,I78,"Unknown") -> Transport | S78: =IF(COUNTBLANK(M78)=0,M78,0) -> 9000 | T78: =IF(COUNTBLANK(K78)=0,K78,"Cash/UPI") -> Cash
A79: TXN1051 | B79: 45709 | C79: May | D79: Shivani Roy | E79: 28 | G79: Freelancing | H79: 55000 | I79: Shopping | J79: 8300 | K79: UPI | L79: 8500 | N79: 699 | O79: Average | P79: =IF(COUNTBLANK(F79)=0,F79,"Unknown") -> Unknown | Q79: =IF(COUNTBLANK(G79)=0,G79,"Unknown") -> Freelancing | R79: =IF(COUNTBLANK(I79)=0,I79,"Unknown") -> Shopping | S79: =IF(COUNTBLANK(M79)=0,M79,0) -> 0 | T79: =IF(COUNTBLANK(K79)=0,K79,"Cash/UPI") -> UPI
A80: TXN1052 | B80: 45710 | C80: June | D80: Manav Jain | E80: 40 | F80: Ahmedabad | G80: Business | H80: 134000 | I80: Investment | J80: 31000 | K80: NetBanking | L80: 39000 | M80: 17000 | N80: 803 | O80: Excellent | P80: =IF(COUNTBLANK(F80)=0,F80,"Unknown") -> Ahmedabad | Q80: =IF(COUNTBLANK(G80)=0,G80,"Unknown") -> Business | R80: =IF(COUNTBLANK(I80)=0,I80,"Unknown") -> Investment | S80: =IF(COUNTBLANK(M80)=0,M80,0) -> 17000 | T80: =IF(COUNTBLANK(K80)=0,K80,"Cash/UPI") -> NetBanking
A81: TXN1053 | B81: 45711 | C81: July | D81: Snehal Patil | E81: 31 | F81: Mumbai | G81: Salary | H81: 76000 | I81: Groceries | J81: 6800 | K81: Card | L81: 14000 | M81: 4000 | N81: 739 | O81: Good | P81: =IF(COUNTBLANK(F81)=0,F81,"Unknown") -> Mumbai | Q81: =IF(COUNTBLANK(G81)=0,G81,"Unknown") -> Salary | R81: =IF(COUNTBLANK(I81)=0,I81,"Unknown") -> Groceries | S81: =IF(COUNTBLANK(M81)=0,M81,0) -> 4000 | T81: =IF(COUNTBLANK(K81)=0,K81,"Cash/UPI") -> Card
A82: TXN1054 | B82: 45712 | C82: August | D82: Rohit Das | E82: 27 | F82: Kolkata | G82: Salary | H82: 61000 | I82: Rent | J82: 17500 | K82: UPI | L82: 10000 | M82: 3500 | N82: 714 | O82: Stable | P82: =IF(COUNTBLANK(F82)=0,F82,"Unknown") -> Kolkata | Q82: =IF(COUNTBLANK(G82)=0,G82,"Unknown") -> Salary | R82: =IF(COUNTBLANK(I82)=0,I82,"Unknown") -> Rent | S82: =IF(COUNTBLANK(M82)=0,M82,0) -> 3500 | T82: =IF(COUNTBLANK(K82)=0,K82,"Cash/UPI") -> UPI
A83: TXN1055 | B83: 45713 | C83: September | D83: Ananya Kapoor | E83: 33 | F83: Delhi | G83: Salary | H83: 85000 | I83: Healthcare | J83: 5200 | K83: NetBanking | L83: 18000 | M83: 8000 | N83: 748 | O83: Good | P83: =IF(COUNTBLANK(F83)=0,F83,"Unknown") -> Delhi | Q83: =IF(COUNTBLANK(G83)=0,G83,"Unknown") -> Salary | R83: =IF(COUNTBLANK(I83)=0,I83,"Unknown") -> Healthcare | S83: =IF(COUNTBLANK(M83)=0,M83,0) -> 8000 | T83: =IF(COUNTBLANK(K83)=0,K83,"Cash/UPI") -> NetBanking
A84: TXN1056 | B84: 45714 | C84: October | D84: Deep Roy | E84: 24 | F84: Kolkata | G84: Internship | H84: 27000 | I84: Food | J84: 3900 | K84: Cash | L84: 2500 | N84: 671 | O84: Average | P84: =IF(COUNTBLANK(F84)=0,F84,"Unknown") -> Kolkata | Q84: =IF(COUNTBLANK(G84)=0,G84,"Unknown") -> Internship | R84: =IF(COUNTBLANK(I84)=0,I84,"Unknown") -> Food | S84: =IF(COUNTBLANK(M84)=0,M84,0) -> 0 | T84: =IF(COUNTBLANK(K84)=0,K84,"Cash/UPI") -> Cash
A85: TXN1057 | B85: 45715 | C85: November | D85: Tarun Singh | E85: 39 | F85: Chandigarh | H85: 126000 | I85: Travel | J85: 11200 | K85: Card | L85: 32000 | M85: 15000 | N85: 791 | O85: Excellent | P85: =IF(COUNTBLANK(F85)=0,F85,"Unknown") -> Chandigarh | Q85: =IF(COUNTBLANK(G85)=0,G85,"Unknown") -> Unknown | R85: =IF(COUNTBLANK(I85)=0,I85,"Unknown") -> Travel | S85: =IF(COUNTBLANK(M85)=0,M85,0) -> 15000 | T85: =IF(COUNTBLANK(K85)=0,K85,"Cash/UPI") -> Card
A86: TXN1058 | B86: 45716 | C86: December | D86: Pooja Sharma | E86: 29 | F86: Jaipur | G86: Salary | H86: 68000 | I86: Shopping | J86: 7200 | K86: UPI | L86: 12000 | M86: 2500 | N86: 733 | O86: Good | P86: =IF(COUNTBLANK(F86)=0,F86,"Unknown") -> Jaipur | Q86: =IF(COUNTBLANK(G86)=0,G86,"Unknown") -> Salary | R86: =IF(COUNTBLANK(I86)=0,I86,"Unknown") -> Shopping | S86: =IF(COUNTBLANK(M86)=0,M86,0) -> 2500 | T86: =IF(COUNTBLANK(K86)=0,K86,"Cash/UPI") -> UPI
A87: TXN1059 | B87: 45717 | C87: January | D87: Abhinav Bose | E87: 36 | F87: Kolkata | G87: Salary | H87: 79000 | I87: Utilities | J87: 6100 | K87: Card | L87: 17000 | M87: 6500 | N87: 742 | O87: Good | P87: =IF(COUNTBLANK(F87)=0,F87,"Unknown") -> Kolkata | Q87: =IF(COUNTBLANK(G87)=0,G87,"Unknown") -> Salary | R87: =IF(COUNTBLANK(I87)=0,I87,"Unknown") -> Utilities | S87: =IF(COUNTBLANK(M87)=0,M87,0) -> 6500 | T87: =IF(COUNTBLANK(K87)=0,K87,"Cash/UPI") -> Card
A88: TXN1060 | B88: 45718 | C88: February | D88: Ritika Das | E88: 25 | F88: Pune | G88: Freelancing | H88: 49000 | I88: Entertainment | J88: 4700 | L88: 6000 | M88: 8000 | N88: 687 | O88: Average | P88: =IF(COUNTBLANK(F88)=0,F88,"Unknown") -> Pune | Q88: =IF(COUNTBLANK(G88)=0,G88,"Unknown") -> Freelancing | R88: =IF(COUNTBLANK(I88)=0,I88,"Unknown") -> Entertainment | S88: =IF(COUNTBLANK(M88)=0,M88,0) -> 8000 | T88: =IF(COUNTBLANK(K88)=0,K88,"Cash/UPI") -> Cash/UPI
A89: TXN1061 | B89: 45719 | C89: March | D89: Vinay Kumar | E89: 42 | F89: Patna | G89: Business | H89: 146000 | I89: Investment | J89: 39000 | K89: Cheque | L89: 47000 | M89: 21000 | N89: 809 | O89: Excellent | P89: =IF(COUNTBLANK(F89)=0,F89,"Unknown") -> Patna | Q89: =IF(COUNTBLANK(G89)=0,G89,"Unknown") -> Business | R89: =IF(COUNTBLANK(I89)=0,I89,"Unknown") -> Investment | S89: =IF(COUNTBLANK(M89)=0,M89,0) -> 21000 | T89: =IF(COUNTBLANK(K89)=0,K89,"Cash/UPI") -> Cheque
A90: TXN1062 | B90: 45720 | C90: April | D90: Neha Sen | E90: 31 | F90: Kolkata | G90: Salary | H90: 71000 | I90: Healthcare | J90: 4500 | K90: UPI | L90: 14000 | M90: 3500 | N90: 737 | O90: Good | P90: =IF(COUNTBLANK(F90)=0,F90,"Unknown") -> Kolkata | Q90: =IF(COUNTBLANK(G90)=0,G90,"Unknown") -> Salary | R90: =IF(COUNTBLANK(I90)=0,I90,"Unknown") -> Healthcare | S90: =IF(COUNTBLANK(M90)=0,M90,0) -> 3500 | T90: =IF(COUNTBLANK(K90)=0,K90,"Cash/UPI") -> UPI
A91: TXN1063 | B91: 45721 | C91: May | D91: Rajat Sharma | E91: 28 | G91: Salary | H91: 64000 | I91: Transport | J91: 5100 | K91: Cash | L91: 11000 | M91: 4000 | N91: 716 | O91: Stable | P91: =IF(COUNTBLANK(F91)=0,F91,"Unknown") -> Unknown | Q91: =IF(COUNTBLANK(G91)=0,G91,"Unknown") -> Salary | R91: =IF(COUNTBLANK(I91)=0,I91,"Unknown") -> Transport | S91: =IF(COUNTBLANK(M91)=0,M91,0) -> 4000 | T91: =IF(COUNTBLANK(K91)=0,K91,"Cash/UPI") -> Cash
A92: TXN1064 | B92: 45722 | C92: June | D92: Ishita Roy | E92: 27 | F92: Kolkata | G92: Freelancing | H92: 54000 | I92: Food | J92: 5900 | K92: Card | L92: 7000 | N92: 697 | O92: Average | P92: =IF(COUNTBLANK(F92)=0,F92,"Unknown") -> Kolkata | Q92: =IF(COUNTBLANK(G92)=0,G92,"Unknown") -> Freelancing | R92: =IF(COUNTBLANK(I92)=0,I92,"Unknown") -> Food | S92: =IF(COUNTBLANK(M92)=0,M92,0) -> 0 | T92: =IF(COUNTBLANK(K92)=0,K92,"Cash/UPI") -> Card
A93: TXN1065 | B93: 45723 | C93: July | D93: Sandeep Jain | E93: 44 | F93: Mumbai | G93: Business | H93: 152000 | I93: Rent | J93: 36000 | K93: NetBanking | L93: 52000 | M93: 24000 | N93: 818 | O93: Excellent | P93: =IF(COUNTBLANK(F93)=0,F93,"Unknown") -> Mumbai | Q93: =IF(COUNTBLANK(G93)=0,G93,"Unknown") -> Business | R93: =IF(COUNTBLANK(I93)=0,I93,"Unknown") -> Rent | S93: =IF(COUNTBLANK(M93)=0,M93,0) -> 24000 | T93: =IF(COUNTBLANK(K93)=0,K93,"Cash/UPI") -> NetBanking
A94: TXN1066 | B94: 45724 | C94: August | D94: Monika Gupta | E94: 30 | F94: Delhi | H94: 73000 | I94: Shopping | J94: 8400 | K94: UPI | L94: 13000 | M94: 5000 | N94: 729 | O94: Good | P94: =IF(COUNTBLANK(F94)=0,F94,"Unknown") -> Delhi | Q94: =IF(COUNTBLANK(G94)=0,G94,"Unknown") -> Unknown | R94: =IF(COUNTBLANK(I94)=0,I94,"Unknown") -> Shopping | S94: =IF(COUNTBLANK(M94)=0,M94,0) -> 5000 | T94: =IF(COUNTBLANK(K94)=0,K94,"Cash/UPI") -> UPI
A95: TXN1067 | B95: 45725 | C95: September | D95: Arjun Das | E95: 35 | F95: Kolkata | G95: Salary | H95: 82000 | I95: Travel | J95: 9800 | K95: Card | L95: 19000 | M95: 9000 | N95: 745 | O95: Good | P95: =IF(COUNTBLANK(F95)=0,F95,"Unknown") -> Kolkata | Q95: =IF(COUNTBLANK(G95)=0,G95,"Unknown") -> Salary | R95: =IF(COUNTBLANK(I95)=0,I95,"Unknown") -> Travel | S95: =IF(COUNTBLANK(M95)=0,M95,0) -> 9000 | T95: =IF(COUNTBLANK(K95)=0,K95,"Cash/UPI") -> Card
A96: TXN1068 | B96: 45726 | C96: October | D96: Preeti Nair | E96: 26 | F96: Kochi | G96: Freelancing | H96: 51000 | J96: 4300 | K96: UPI | L96: 6500 | M96: 7000 | N96: 692 | O96: Average | P96: =IF(COUNTBLANK(F96)=0,F96,"Unknown") -> Kochi | Q96: =IF(COUNTBLANK(G96)=0,G96,"Unknown") -> Freelancing | R96: =IF(COUNTBLANK(I96)=0,I96,"Unknown") -> Unknown | S96: =IF(COUNTBLANK(M96)=0,M96,0) -> 7000 | T96: =IF(COUNTBLANK(K96)=0,K96,"Cash/UPI") -> UPI
A97: TXN1069 | B97: 45727 | C97: November | D97: Kishore Patel | E97: 41 | F97: Ahmedabad | G97: Business | H97: 129000 | I97: Investment | J97: 30000 | K97: Cheque | L97: 36000 | M97: 16000 | N97: 796 | O97: Excellent | P97: =IF(COUNTBLANK(F97)=0,F97,"Unknown") -> Ahmedabad | Q97: =IF(COUNTBLANK(G97)=0,G97,"Unknown") -> Business | R97: =IF(COUNTBLANK(I97)=0,I97,"Unknown") -> Investment | S97: =IF(COUNTBLANK(M97)=0,M97,0) -> 16000 | T97: =IF(COUNTBLANK(K97)=0,K97,"Cash/UPI") -> Cheque
A98: TXN1070 | B98: 45728 | C98: December | D98: Simran Das | E98: 32 | F98: Kolkata | G98: Salary | H98: 69000 | I98: Groceries | J98: 6700 | K98: Card | L98: 12500 | M98: 3000 | N98: 734 | O98: Good | P98: =IF(COUNTBLANK(F98)=0,F98,"Unknown") -> Kolkata | Q98: =IF(COUNTBLANK(G98)=0,G98,"Unknown") -> Salary | R98: =IF(COUNTBLANK(I98)=0,I98,"Unknown") -> Groceries | S98: =IF(COUNTBLANK(M98)=0,M98,0) -> 3000 | T98: =IF(COUNTBLANK(K98)=0,K98,"Cash/UPI") -> Card
A99: TXN1071 | B99: 45729 | C99: January | D99: Aditya Singh | E99: 29 | F99: Delhi | G99: Salary | H99: 66000 | I99: Rent | J99: 20000 | K99: UPI | L99: 9000 | M99: 4500 | N99: 710 | O99: Stable | P99: =IF(COUNTBLANK(F99)=0,F99,"Unknown") -> Delhi | Q99: =IF(COUNTBLANK(G99)=0,G99,"Unknown") -> Salary | R99: =IF(COUNTBLANK(I99)=0,I99,"Unknown") -> Rent | S99: =IF(COUNTBLANK(M99)=0,M99,0) -> 4500 | T99: =IF(COUNTBLANK(K99)=0,K99,"Cash/UPI") -> UPI
A100: TXN1072 | B100: 45730 | C100: February | D100: Payal Roy | E100: 24 | H100: 32000 | J100: 3900 | L100: 3500 | N100: 678 | O100: Average | P100: =IF(COUNTBLANK(F100)=0,F100,"Unknown") -> Unknown | Q100: =IF(COUNTBLANK(G100)=0,G100,"Unknown") -> Unknown | R100: =IF(COUNTBLANK(I100)=0,I100,"Unknown") -> Unknown | S100: =IF(COUNTBLANK(M100)=0,M100,0) -> 0 | T100: =IF(COUNTBLANK(K100)=0,K100,"Cash/UPI") -> Cash/UPI

Sheet Cleaned Data
A1: CLEANED DATA
A2: Id | B2: Date | C2: Month | D2: Person Name | E2: Age | F2: City | G2: Income Source | H2: Monthly Income | I2: Expense Category | J2: Expense Amount | K2: Payment Method | L2: Savings | M2: Loan EMI | N2: Credit Score | O2: Financial Status
A3: TXN1001 | B3: 45659 | C3: January | D3: Rahul Sen | E3: 29 | F3: =_xlfn.XLOOKUP(D3,'Cleaning Tasks'!D3:D100,'Cleaning Tasks'!P3:P100) -> Kolkata | G3: =_xlfn.XLOOKUP(D3,'Cleaned Data'!D3:D100,'Cleaning Tasks'!Q3:Q100) -> Salary | H3: =_xlfn.XLOOKUP(D3,'Cleaning Tasks'!D3:D100,'Cleaning Tasks'!H3:H100) -> 65000 | I3: =_xlfn.XLOOKUP(D3,'Cleaning Tasks'!D3:D100,'Cleaning Tasks'!R3:R100) -> Rent | J3: 18000 | K3: UPI | L3: 12000 | M3: =_xlfn.XLOOKUP(D3,'Cleaning Tasks'!D3:D100,'Cleaning Tasks'!S3:S100) -> 5000 | N3: 742 | O3: Stable
A4: TXN1002 | B4: 45660 | C4: February | D4: Priya Das | E4: 34 | F4: =_xlfn.XLOOKUP(D4,'Cleaning Tasks'!D4:D101,'Cleaning Tasks'!P4:P101) -> Mumbai | G4: =_xlfn.XLOOKUP(D4,'Cleaned Data'!D4:D101,'Cleaning Tasks'!Q4:Q101) -> Freelancing | H4: =_xlfn.XLOOKUP(D4,'Cleaning Tasks'!D4:D101,'Cleaning Tasks'!H4:H101) -> 72000 | I4: =_xlfn.XLOOKUP(D4,'Cleaning Tasks'!D4:D101,'Cleaning Tasks'!R4:R101) -> Groceries | J4: 6500 | K4: Card | L4: 15000 | M4: =_xlfn.XLOOKUP(D4,'Cleaning Tasks'!D4:D101,'Cleaning Tasks'!S4:S101) -> 0 | N4: 788 | O4: Good
A5: TXN1003 | B5: 45661 | C5: March | D5: Ankit Roy | E5: 26 | F5: =_xlfn.XLOOKUP(D5,'Cleaning Tasks'!D5:D102,'Cleaning Tasks'!P5:P102) -> Unknown | G5: =_xlfn.XLOOKUP(D5,'Cleaned Data'!D5:D102,'Cleaning Tasks'!Q5:Q102) -> Salary | H5: =_xlfn.XLOOKUP(D5,'Cleaning Tasks'!D5:D102,'Cleaning Tasks'!H5:H102) -> 54000 | I5: =_xlfn.XLOOKUP(D5,'Cleaning Tasks'!D5:D102,'Cleaning Tasks'!R5:R102) -> Unknown | J5: 3200 | K5: Cash | L5: 8000 | M5: =_xlfn.XLOOKUP(D5,'Cleaning Tasks'!D5:D102,'Cleaning Tasks'!S5:S102) -> 2500 | N5: 689 | O5: Average
A6: TXN1004 | B6: 45662 | C6: April | D6: Sneha Paul | E6: 31 | F6: =_xlfn.XLOOKUP(D6,'Cleaning Tasks'!D6:D103,'Cleaning Tasks'!P6:P103) -> Bangalore | G6: =_xlfn.XLOOKUP(D6,'Cleaned Data'!D6:D103,'Cleaning Tasks'!Q6:Q103) -> Business | H6: =_xlfn.XLOOKUP(D6,'Cleaning Tasks'!D6:D103,'Cleaning Tasks'!H6:H103) -> 98000 | I6: =_xlfn.XLOOKUP(D6,'Cleaning Tasks'!D6:D103,'Cleaning Tasks'!R6:R103) -> Utilities | J6: 5400 | K6: NetBanking | L6: 25000 | M6: =_xlfn.XLOOKUP(D6,'Cleaning Tasks'!D6:D103,'Cleaning Tasks'!S6:S103) -> 8000 | N6: 801 | O6: Excellent
A7: TXN1005 | B7: 45663 | C7: May | D7: Rohan Mitra | E7: 38 | F7: =_xlfn.XLOOKUP(D7,'Cleaning Tasks'!D7:D104,'Cleaning Tasks'!P7:P104) -> Hyderabad | G7: =_xlfn.XLOOKUP(D7,'Cleaned Data'!D7:D104,'Cleaning Tasks'!Q7:Q104) -> Salary | H7: =_xlfn.XLOOKUP(D7,'Cleaning Tasks'!D7:D104,'Cleaning Tasks'!H7:H104) -> 85000 | I7: =_xlfn.XLOOKUP(D7,'Cleaning Tasks'!D7:D104,'Cleaning Tasks'!R7:R104) -> Entertainment | J7: 7600 | K7: Card | L7: 10000 | M7: =_xlfn.XLOOKUP(D7,'Cleaning Tasks'!D7:D104,'Cleaning Tasks'!S7:S104) -> 12000 | N7: 655 | O7: Risky
A8: TXN1006 | B8: 45664 | C8: June | D8: Aditi Sharma | E8: 27 | F8: =_xlfn.XLOOKUP(D8,'Cleaning Tasks'!D8:D105,'Cleaning Tasks'!P8:P105) -> Pune | G8: =_xlfn.XLOOKUP(D8,'Cleaned Data'!D8:D105,'Cleaning Tasks'!Q8:Q105) -> Salary | H8: =_xlfn.XLOOKUP(D8,'Cleaning Tasks'!D8:D105,'Cleaning Tasks'!H8:H105) -> 61000 | I8: =_xlfn.XLOOKUP(D8,'Cleaning Tasks'!D8:D105,'Cleaning Tasks'!R8:R105) -> Healthcare | J8: 2400 | K8: UPI | L8: 17000 | M8: =_xlfn.XLOOKUP(D8,'Cleaning Tasks'!D8:D105,'Cleaning Tasks'!S8:S105) -> 0 | N8: 771 | O8: Good
A9: TXN1007 | B9: 45665 | C9: July | D9: Karan Singh | E9: 42 | F9: =_xlfn.XLOOKUP(D9,'Cleaning Tasks'!D9:D106,'Cleaning Tasks'!P9:P106) -> Chennai | G9: =_xlfn.XLOOKUP(D9,'Cleaned Data'!D9:D106,'Cleaning Tasks'!Q9:Q106) -> Business | H9: =_xlfn.XLOOKUP(D9,'Cleaning Tasks'!D9:D106,'Cleaning Tasks'!H9:H106) -> 120000 | I9: =_xlfn.XLOOKUP(D9,'Cleaning Tasks'!D9:D106,'Cleaning Tasks'!R9:R106) -> Rent | J9: 25000 | K9: Cheque | L9: 35000 | M9: =_xlfn.XLOOKUP(D9,'Cleaning Tasks'!D9:D106,'Cleaning Tasks'!S9:S106) -> 18000 | N9: 720 | O9: Stable
A10: TXN1008 | B10: 45666 | C10: August | D10: Megha Dutta | E10: 24 | F10: =_xlfn.XLOOKUP(D10,'Cleaning Tasks'!D10:D107,'Cleaning Tasks'!P10:P107) -> Kolkata | G10: =_xlfn.XLOOKUP(D10,'Cleaned Data'!D10:D107,'Cleaning Tasks'!Q10:Q107) -> Internship | H10: =_xlfn.XLOOKUP(D10,'Cleaning Tasks'!D10:D107,'Cleaning Tasks'!H10:H107) -> 28000 | I10: =_xlfn.XLOOKUP(D10,'Cleaning Tasks'!D10:D107,'Cleaning Tasks'!R10:R107) -> Education | J10: 4500 | K10: UPI | L10: 5000 | M10: =_xlfn.XLOOKUP(D10,'Cleaning Tasks'!D10:D107,'Cleaning Tasks'!S10:S107) -> 0 | N10: 690 | O10: Average
A11: TXN1009 | B11: 45667 | C11: September | D11: Arjun Nair | E11: 36 | F11: =_xlfn.XLOOKUP(D11,'Cleaning Tasks'!D11:D108,'Cleaning Tasks'!P11:P108) -> Kochi | G11: =_xlfn.XLOOKUP(D11,'Cleaned Data'!D11:D108,'Cleaning Tasks'!Q11:Q108) -> Salary | H11: =_xlfn.XLOOKUP(D11,'Cleaning Tasks'!D11:D108,'Cleaning Tasks'!H11:H108) -> 76000 | I11: =_xlfn.XLOOKUP(D11,'Cleaning Tasks'!D11:D108,'Cleaning Tasks'!R11:R108) -> Unknown | J11: 8200 | K11: Card | L11: 14000 | M11: =_xlfn.XLOOKUP(D11,'Cleaning Tasks'!D11:D108,'Cleaning Tasks'!S11:S108) -> 7000 | N11: 745 | O11: Stable
A12: TXN1010 | B12: 45668 | C12: October | D12: Neha Kapoor | E12: 30 | F12: =_xlfn.XLOOKUP(D12,'Cleaning Tasks'!D12:D109,'Cleaning Tasks'!P12:P109) -> Jaipur | G12: =_xlfn.XLOOKUP(D12,'Cleaned Data'!D12:D109,'Cleaning Tasks'!Q12:Q109) -> Freelancing | H12: =_xlfn.XLOOKUP(D12,'Cleaning Tasks'!D12:D109,'Cleaning Tasks'!H12:H109) -> 68000 | I12: =_xlfn.XLOOKUP(D12,'Cleaning Tasks'!D12:D109,'Cleaning Tasks'!R12:R109) -> Shopping | J12: 9200 | K12: UPI | L12: 11000 | M12: =_xlfn.XLOOKUP(D12,'Cleaning Tasks'!D12:D109,'Cleaning Tasks'!S12:S109) -> 3000 | N12: 732 | O12: Good
A13: TXN1011 | B13: 45669 | C13: November | D13: Vikram Bose | E13: 45 | F13: =_xlfn.XLOOKUP(D13,'Cleaning Tasks'!D13:D110,'Cleaning Tasks'!P13:P110) -> Kolkata | G13: =_xlfn.XLOOKUP(D13,'Cleaned Data'!D13:D110,'Cleaning Tasks'!Q13:Q110) -> Business | H13: =_xlfn.XLOOKUP(D13,'Cleaning Tasks'!D13:D110,'Cleaning Tasks'!H13:H110) -> 150000 | I13: =_xlfn.XLOOKUP(D13,'Cleaning Tasks'!D13:D110,'Cleaning Tasks'!R13:R110) -> Investment | J13: 35000 | K13: NetBanking | L13: 40000 | M13: =_xlfn.XLOOKUP(D13,'Cleaning Tasks'!D13:D110,'Cleaning Tasks'!S13:S110) -> 20000 | N13: 810 | O13: Excellent
A14: TXN1012 | B14: 45670 | C14: December | D14: Isha Jain | E14: 28 | F14: =_xlfn.XLOOKUP(D14,'Cleaning Tasks'!D14:D111,'Cleaning Tasks'!P14:P111) -> Delhi | G14: =_xlfn.XLOOKUP(D14,'Cleaned Data'!D14:D111,'Cleaning Tasks'!Q14:Q111) -> Unknown | H14: =_xlfn.XLOOKUP(D14,'Cleaning Tasks'!D14:D111,'Cleaning Tasks'!H14:H111) -> 59000 | I14: =_xlfn.XLOOKUP(D14,'Cleaning Tasks'!D14:D111,'Cleaning Tasks'!R14:R111) -> Food | J14: 5800 | K14: Cash/UPI | L14: 9000 | M14: =_xlfn.XLOOKUP(D14,'Cleaning Tasks'!D14:D111,'Cleaning Tasks'!S14:S111) -> 2500 | N14: 704 | O14: Stable
... A100: TXN1072 | B100: 45730 | C100: February | D100: Payal Roy | E100: 24 | F100: =_xlfn.XLOOKUP(D100,'Cleaning Tasks'!D100:D197,'Cleaning Tasks'!P100:P197) -> Unknown | G100: =_xlfn.XLOOKUP(D100,'Cleaned Data'!D100:D197,'Cleaning Tasks'!Q100:Q197) -> Unknown | H100: =_xlfn.XLOOKUP(D100,'Cleaning Tasks'!D100:D197,'Cleaning Tasks'!H100:H197) -> 32000 | I100: =_xlfn.XLOOKUP(D100,'Cleaning Tasks'!D100:D197,'Cleaning Tasks'!R100:R197) -> Unknown | J100: 3900 | K100: Cash/UPI | L100: 3500 | M100: =_xlfn.XLOOKUP(D100,'Cleaning Tasks'!D100:D197,'Cleaning Tasks'!S100:S197) -> 0 | N100: 678 | O100: Average

Sheet Income Analysis
A1: 📈 INCOME ANALYSIS — SOURCE & MONTHLY BREAKDOWN | N1: Go to Welcome Page
A2: ▌ MONTHLY INCOME SUMMARY
A3: Income Source | B3: January | C3: February | D3: March | E3: April | F3: May | G3: June | H3: July | I3: August | J3: September | K3: October | L3: November | M3: December | N3: TOTAL
A4: {=_xlfn.UNIQUE('Cleaned Data'!G3:G100)} -> Salary | B4: =SUMIFS('Cleaned Data'!$H$3:$H$100,'Cleaned Data'!$G$3:$G$100,$A4,'Cleaned Data'!$C$3:$C$100,B$3) -> 605000 | C4: =SUMIFS('Cleaned Data'!$H$3:$H$100,'Cleaned Data'!$G$3:$G$100,$A4,'Cleaned Data'!$C$3:$C$100,C$3) -> 246000 | D4: =SUMIFS('Cleaned Data'!$H$3:$H$100,'Cleaned Data'!$G$3:$G$100,$A4,'Cleaned Data'!$C$3:$C$100,D$3) -> 124000 | E4: =SUMIFS('Cleaned Data'!$H$3:$H$100,'Cleaned Data'!$G$3:$G$100,$A4,'Cleaned Data'!$C$3:$C$100,E$3) -> 284000 | F4: =SUMIFS('Cleaned Data'!$H$3:$H$100,'Cleaned Data'!$G$3:$G$100,$A4,'Cleaned Data'!$C$3:$C$100,F$3) -> 373000 | G4: =SUMIFS('Cleaned Data'!$H$3:$H$100,'Cleaned Data'!$G$3:$G$100,$A4,'Cleaned Data'!$C$3:$C$100,G$3) -> 212000 | H4: =SUMIFS('Cleaned Data'!$H$3:$H$100,'Cleaned Data'!$G$3:$G$100,$A4,'Cleaned Data'!$C$3:$C$100,H$3) -> 159000 | I4: =SUMIFS('Cleaned Data'!$H$3:$H$100,'Cleaned Data'!$G$3:$G$100,$A4,'Cleaned Data'!$C$3:$C$100,I$3) -> 222000 | ... M4: =SUMIFS('Cleaned Data'!$H$3:$H$100,'Cleaned Data'!$G$3:$G$100,$A4,'Cleaned Data'!$C$3:$C$100,M$3) -> 280000 | N4: =SUM(B4:M4) -> 3235000
A5: Freelancing | B5: =SUMIFS('Cleaned Data'!$H$3:$H$100,'Cleaned Data'!$G$3:$G$100,$A5,'Cleaned Data'!$C$3:$C$100,B$3) -> 0 | C5: =SUMIFS('Cleaned Data'!$H$3:$H$100,'Cleaned Data'!$G$3:$G$100,$A5,'Cleaned Data'!$C$3:$C$100,C$3) -> 168000 | D5: =SUMIFS('Cleaned Data'!$H$3:$H$100,'Cleaned Data'!$G$3:$G$100,$A5,'Cleaned Data'!$C$3:$C$100,D$3) -> 109000 | E5: =SUMIFS('Cleaned Data'!$H$3:$H$100,'Cleaned Data'!$G$3:$G$100,$A5,'Cleaned Data'!$C$3:$C$100,E$3) -> 0 | F5: =SUMIFS('Cleaned Data'!$H$3:$H$100,'Cleaned Data'!$G$3:$G$100,$A5,'Cleaned Data'!$C$3:$C$100,F$3) -> 106000 | G5: =SUMIFS('Cleaned Data'!$H$3:$H$100,'Cleaned Data'!$G$3:$G$100,$A5,'Cleaned Data'!$C$3:$C$100,G$3) -> 110000 | H5: =SUMIFS('Cleaned Data'!$H$3:$H$100,'Cleaned Data'!$G$3:$G$100,$A5,'Cleaned Data'!$C$3:$C$100,H$3) -> 155000 | I5: =SUMIFS('Cleaned Data'!$H$3:$H$100,'Cleaned Data'!$G$3:$G$100,$A5,'Cleaned Data'!$C$3:$C$100,I$3) -> 0 | ... M5: =SUMIFS('Cleaned Data'!$H$3:$H$100,'Cleaned Data'!$G$3:$G$100,$A5,'Cleaned Data'!$C$3:$C$100,M$3) -> 64000 | N5: =SUM(B5:M5) -> 992000
A6: Business | B6: =SUMIFS('Cleaned Data'!$H$3:$H$100,'Cleaned Data'!$G$3:$G$100,$A6,'Cleaned Data'!$C$3:$C$100,B$3) -> 0 | C6: =SUMIFS('Cleaned Data'!$H$3:$H$100,'Cleaned Data'!$G$3:$G$100,$A6,'Cleaned Data'!$C$3:$C$100,C$3) -> 155000 | D6: =SUMIFS('Cleaned Data'!$H$3:$H$100,'Cleaned Data'!$G$3:$G$100,$A6,'Cleaned Data'!$C$3:$C$100,D$3) -> 278000 | E6: =SUMIFS('Cleaned Data'!$H$3:$H$100,'Cleaned Data'!$G$3:$G$100,$A6,'Cleaned Data'!$C$3:$C$100,E$3) -> 533000 | F6: =SUMIFS('Cleaned Data'!$H$3:$H$100,'Cleaned Data'!$G$3:$G$100,$A6,'Cleaned Data'!$C$3:$C$100,F$3) -> 0 | G6: =SUMIFS('Cleaned Data'!$H$3:$H$100,'Cleaned Data'!$G$3:$G$100,$A6,'Cleaned Data'!$C$3:$C$100,G$3) -> 252000 | H6: =SUMIFS('Cleaned Data'!$H$3:$H$100,'Cleaned Data'!$G$3:$G$100,$A6,'Cleaned Data'!$C$3:$C$100,H$3) -> 417000 | I6: =SUMIFS('Cleaned Data'!$H$3:$H$100,'Cleaned Data'!$G$3:$G$100,$A6,'Cleaned Data'!$C$3:$C$100,I$3) -> 139000 | ... M6: =SUMIFS('Cleaned Data'!$H$3:$H$100,'Cleaned Data'!$G$3:$G$100,$A6,'Cleaned Data'!$C$3:$C$100,M$3) -> 292000 | N6: =SUM(B6:M6) -> 2487000
A7: Internship | B7: =SUMIFS('Cleaned Data'!$H$3:$H$100,'Cleaned Data'!$G$3:$G$100,$A7,'Cleaned Data'!$C$3:$C$100,B$3) -> 0 | C7: =SUMIFS('Cleaned Data'!$H$3:$H$100,'Cleaned Data'!$G$3:$G$100,$A7,'Cleaned Data'!$C$3:$C$100,C$3) -> 0 | D7: =SUMIFS('Cleaned Data'!$H$3:$H$100,'Cleaned Data'!$G$3:$G$100,$A7,'Cleaned Data'!$C$3:$C$100,D$3) -> 59000 | E7: =SUMIFS('Cleaned Data'!$H$3:$H$100,'Cleaned Data'!$G$3:$G$100,$A7,'Cleaned Data'!$C$3:$C$100,E$3) -> 0 | F7: =SUMIFS('Cleaned Data'!$H$3:$H$100,'Cleaned Data'!$G$3:$G$100,$A7,'Cleaned Data'!$C$3:$C$100,F$3) -> 0 | G7: =SUMIFS('Cleaned Data'!$H$3:$H$100,'Cleaned Data'!$G$3:$G$100,$A7,'Cleaned Data'!$C$3:$C$100,G$3) -> 0 | H7: =SUMIFS('Cleaned Data'!$H$3:$H$100,'Cleaned Data'!$G$3:$G$100,$A7,'Cleaned Data'!$C$3:$C$100,H$3) -> 0 | I7: =SUMIFS('Cleaned Data'!$H$3:$H$100,'Cleaned Data'!$G$3:$G$100,$A7,'Cleaned Data'!$C$3:$C$100,I$3) -> 59000 | ... M7: =SUMIFS('Cleaned Data'!$H$3:$H$100,'Cleaned Data'!$G$3:$G$100,$A7,'Cleaned Data'!$C$3:$C$100,M$3) -> 0 | N7: =SUM(B7:M7) -> 176000
A8: Unknown | B8: =SUMIFS('Cleaned Data'!$H$3:$H$100,'Cleaned Data'!$G$3:$G$100,$A8,'Cleaned Data'!$C$3:$C$100,B$3) -> 0 | C8: =SUMIFS('Cleaned Data'!$H$3:$H$100,'Cleaned Data'!$G$3:$G$100,$A8,'Cleaned Data'!$C$3:$C$100,C$3) -> 112000 | D8: =SUMIFS('Cleaned Data'!$H$3:$H$100,'Cleaned Data'!$G$3:$G$100,$A8,'Cleaned Data'!$C$3:$C$100,D$3) -> 0 | E8: =SUMIFS('Cleaned Data'!$H$3:$H$100,'Cleaned Data'!$G$3:$G$100,$A8,'Cleaned Data'!$C$3:$C$100,E$3) -> 0 | F8: =SUMIFS('Cleaned Data'!$H$3:$H$100,'Cleaned Data'!$G$3:$G$100,$A8,'Cleaned Data'!$C$3:$C$100,F$3) -> 73000 | G8: =SUMIFS('Cleaned Data'!$H$3:$H$100,'Cleaned Data'!$G$3:$G$100,$A8,'Cleaned Data'!$C$3:$C$100,G$3) -> 0 | H8: =SUMIFS('Cleaned Data'!$H$3:$H$100,'Cleaned Data'!$G$3:$G$100,$A8,'Cleaned Data'!$C$3:$C$100,H$3) -> 0 | I8: =SUMIFS('Cleaned Data'!$H$3:$H$100,'Cleaned Data'!$G$3:$G$100,$A8,'Cleaned Data'!$C$3:$C$100,I$3) -> 210000 | ... M8: =SUMIFS('Cleaned Data'!$H$3:$H$100,'Cleaned Data'!$G$3:$G$100,$A8,'Cleaned Data'!$C$3:$C$100,M$3) -> 59000 | N8: =SUM(B8:M8) -> 916000
A9: Salary | B9: =SUMIFS('Cleaned Data'!$H$3:$H$100,'Cleaned Data'!$G$3:$G$100,$A9,'Cleaned Data'!$C$3:$C$100,B$3) -> 0 | C9: =SUMIFS('Cleaned Data'!$H$3:$H$100,'Cleaned Data'!$G$3:$G$100,$A9,'Cleaned Data'!$C$3:$C$100,C$3) -> 0 | D9: =SUMIFS('Cleaned Data'!$H$3:$H$100,'Cleaned Data'!$G$3:$G$100,$A9,'Cleaned Data'!$C$3:$C$100,D$3) -> 0 | E9: =SUMIFS('Cleaned Data'!$H$3:$H$100,'Cleaned Data'!$G$3:$G$100,$A9,'Cleaned Data'!$C$3:$C$100,E$3) -> 0 | F9: =SUMIFS('Cleaned Data'!$H$3:$H$100,'Cleaned Data'!$G$3:$G$100,$A9,'Cleaned Data'!$C$3:$C$100,F$3) -> 0 | G9: =SUMIFS('Cleaned Data'!$H$3:$H$100,'Cleaned Data'!$G$3:$G$100,$A9,'Cleaned Data'!$C$3:$C$100,G$3) -> 65000 | H9: =SUMIFS('Cleaned Data'!$H$3:$H$100,'Cleaned Data'!$G$3:$G$100,$A9,'Cleaned Data'!$C$3:$C$100,H$3) -> 0 | I9: =SUMIFS('Cleaned Data'!$H$3:$H$100,'Cleaned Data'!$G$3:$G$100,$A9,'Cleaned Data'!$C$3:$C$100,I$3) -> 0 | ... M9: =SUMIFS('Cleaned Data'!$H$3:$H$100,'Cleaned Data'!$G$3:$G$100,$A9,'Cleaned Data'!$C$3:$C$100,M$3) -> 0 | N9: =SUM(B9:M9) -> 65000
A10: GRAND TOTAL | B10: =SUM(B4:B9) -> 605000 | C10: =SUM(C4:C9) -> 681000 | D10: =SUM(D4:D9) -> 570000 | E10: =SUM(E4:E9) -> 817000 | F10: =SUM(F4:F9) -> 552000 | G10: =SUM(G4:G9) -> 639000 | H10: =SUM(H4:H9) -> 731000 | I10: =SUM(I4:I9) -> 630000 | ... N10: =SUM(N4:N9) -> 7871000
Q12: i

Sheet Expense Analysis
A1: 💸 EXPENSE ANALYSIS — CATEGORY BREAKDOWN | O1: Go to Welcome Page
A3: Expense Category | B3: January | C3: February | D3: March | E3: April | F3: May | G3: June | H3: July | I3: August | J3: September | K3: October | L3: November | M3: December | N3: TOTAL | O3: % OF TOTAL
A4: {=_xlfn.UNIQUE('Cleaned Data'!I3:I100)} -> Rent | B4: =SUMIFS('Cleaned Data'!$J:$J,'Cleaned Data'!$I:$I,$A4,'Cleaned Data'!$C:$C,B$3) -> 78000 | C4: =SUMIFS('Cleaned Data'!$J:$J,'Cleaned Data'!$I:$I,$A4,'Cleaned Data'!$C:$C,C$3) -> 56000 | D4: =SUMIFS('Cleaned Data'!$J:$J,'Cleaned Data'!$I:$I,$A4,'Cleaned Data'!$C:$C,D$3) -> 0 | E4: =SUMIFS('Cleaned Data'!$J:$J,'Cleaned Data'!$I:$I,$A4,'Cleaned Data'!$C:$C,E$3) -> 0 | F4: =SUMIFS('Cleaned Data'!$J:$J,'Cleaned Data'!$I:$I,$A4,'Cleaned Data'!$C:$C,F$3) -> 0 | G4: =SUMIFS('Cleaned Data'!$J:$J,'Cleaned Data'!$I:$I,$A4,'Cleaned Data'!$C:$C,G$3) -> 46000 | H4: =SUMIFS('Cleaned Data'!$J:$J,'Cleaned Data'!$I:$I,$A4,'Cleaned Data'!$C:$C,H$3) -> 61000 | I4: =SUMIFS('Cleaned Data'!$J:$J,'Cleaned Data'!$I:$I,$A4,'Cleaned Data'!$C:$C,I$3) -> 50500 | ... M4: =SUMIFS('Cleaned Data'!$J:$J,'Cleaned Data'!$I:$I,$A4,'Cleaned Data'!$C:$C,M$3) -> 0 | N4: =SUM(B4:M4) -> 327000 | O4: =N4/$N$16 -> 0.28686727
A5: Groceries | B5: =SUMIFS('Cleaned Data'!$J:$J,'Cleaned Data'!$I:$I,$A5,'Cleaned Data'!$C:$C,B$3) -> 6200 | C5: =SUMIFS('Cleaned Data'!$J:$J,'Cleaned Data'!$I:$I,$A5,'Cleaned Data'!$C:$C,C$3) -> 6500 | D5: =SUMIFS('Cleaned Data'!$J:$J,'Cleaned Data'!$I:$I,$A5,'Cleaned Data'!$C:$C,D$3) -> 0 | E5: =SUMIFS('Cleaned Data'!$J:$J,'Cleaned Data'!$I:$I,$A5,'Cleaned Data'!$C:$C,E$3) -> 5900 | F5: =SUMIFS('Cleaned Data'!$J:$J,'Cleaned Data'!$I:$I,$A5,'Cleaned Data'!$C:$C,F$3) -> 0 | G5: =SUMIFS('Cleaned Data'!$J:$J,'Cleaned Data'!$I:$I,$A5,'Cleaned Data'!$C:$C,G$3) -> 0 | H5: =SUMIFS('Cleaned Data'!$J:$J,'Cleaned Data'!$I:$I,$A5,'Cleaned Data'!$C:$C,H$3) -> 6800 | I5: =SUMIFS('Cleaned Data'!$J:$J,'Cleaned Data'!$I:$I,$A5,'Cleaned Data'!$C:$C,I$3) -> 0 | ... M5: =SUMIFS('Cleaned Data'!$J:$J,'Cleaned Data'!$I:$I,$A5,'Cleaned Data'!$C:$C,M$3) -> 13100 | N5: =SUM(B5:M5) -> 38500 | O5: =N5/$N$16 -> 0.033774893
A6: Unknown | B6: =SUMIFS('Cleaned Data'!$J:$J,'Cleaned Data'!$I:$I,$A6,'Cleaned Data'!$C:$C,B$3) -> 8600 | C6: =SUMIFS('Cleaned Data'!$J:$J,'Cleaned Data'!$I:$I,$A6,'Cleaned Data'!$C:$C,C$3) -> 3900 | D6: =SUMIFS('Cleaned Data'!$J:$J,'Cleaned Data'!$I:$I,$A6,'Cleaned Data'!$C:$C,D$3) -> 3200 | E6: =SUMIFS('Cleaned Data'!$J:$J,'Cleaned Data'!$I:$I,$A6,'Cleaned Data'!$C:$C,E$3) -> 0 | F6: =SUMIFS('Cleaned Data'!$J:$J,'Cleaned Data'!$I:$I,$A6,'Cleaned Data'!$C:$C,F$3) -> 10800 | G6: =SUMIFS('Cleaned Data'!$J:$J,'Cleaned Data'!$I:$I,$A6,'Cleaned Data'!$C:$C,G$3) -> 19400 | H6: =SUMIFS('Cleaned Data'!$J:$J,'Cleaned Data'!$I:$I,$A6,'Cleaned Data'!$C:$C,H$3) -> 0 | I6: =SUMIFS('Cleaned Data'!$J:$J,'Cleaned Data'!$I:$I,$A6,'Cleaned Data'!$C:$C,I$3) -> 0 | ... M6: =SUMIFS('Cleaned Data'!$J:$J,'Cleaned Data'!$I:$I,$A6,'Cleaned Data'!$C:$C,M$3) -> 0 | N6: =SUM(B6:M6) -> 58400 | O6: =N6/$N$16 -> 0.051232564
A7: Utilities | B7: =SUMIFS('Cleaned Data'!$J:$J,'Cleaned Data'!$I:$I,$A7,'Cleaned Data'!$C:$C,B$3) -> 6100 | C7: =SUMIFS('Cleaned Data'!$J:$J,'Cleaned Data'!$I:$I,$A7,'Cleaned Data'!$C:$C,C$3) -> 0 | D7: =SUMIFS('Cleaned Data'!$J:$J,'Cleaned Data'!$I:$I,$A7,'Cleaned Data'!$C:$C,D$3) -> 0 | E7: =SUMIFS('Cleaned Data'!$J:$J,'Cleaned Data'!$I:$I,$A7,'Cleaned Data'!$C:$C,E$3) -> 5400 | F7: =SUMIFS('Cleaned Data'!$J:$J,'Cleaned Data'!$I:$I,$A7,'Cleaned Data'!$C:$C,F$3) -> 6300 | G7: =SUMIFS('Cleaned Data'!$J:$J,'Cleaned Data'!$I:$I,$A7,'Cleaned Data'!$C:$C,G$3) -> 0 | H7: =SUMIFS('Cleaned Data'!$J:$J,'Cleaned Data'!$I:$I,$A7,'Cleaned Data'!$C:$C,H$3) -> 15000 | I7: =SUMIFS('Cleaned Data'!$J:$J,'Cleaned Data'!$I:$I,$A7,'Cleaned Data'!$C:$C,I$3) -> 0 | ... M7: =SUMIFS('Cleaned Data'!$J:$J,'Cleaned Data'!$I:$I,$A7,'Cleaned Data'!$C:$C,M$3) -> 0 | N7: =SUM(B7:M7) -> 44800 | O7: =N7/$N$16 -> 0.039301693
A8: Entertainment | B8: =SUMIFS('Cleaned Data'!$J:$J,'Cleaned Data'!$I:$I,$A8,'Cleaned Data'!$C:$C,B$3) -> 0 | C8: =SUMIFS('Cleaned Data'!$J:$J,'Cleaned Data'!$I:$I,$A8,'Cleaned Data'!$C:$C,C$3) -> 8900 | D8: =SUMIFS('Cleaned Data'!$J:$J,'Cleaned Data'!$I:$I,$A8,'Cleaned Data'!$C:$C,D$3) -> 8900 | E8: =SUMIFS('Cleaned Data'!$J:$J,'Cleaned Data'!$I:$I,$A8,'Cleaned Data'!$C:$C,E$3) -> 0 | F8: =SUMIFS('Cleaned Data'!$J:$J,'Cleaned Data'!$I:$I,$A8,'Cleaned Data'!$C:$C,F$3) -> 7600 | G8: =SUMIFS('Cleaned Data'!$J:$J,'Cleaned Data'!$I:$I,$A8,'Cleaned Data'!$C:$C,G$3) -> 0 | H8: =SUMIFS('Cleaned Data'!$J:$J,'Cleaned Data'!$I:$I,$A8,'Cleaned Data'!$C:$C,H$3) -> 4500 | I8: =SUMIFS('Cleaned Data'!$J:$J,'Cleaned Data'!$I:$I,$A8,'Cleaned Data'!$C:$C,I$3) -> 0 | ... M8: =SUMIFS('Cleaned Data'!$J:$J,'Cleaned Data'!$I:$I,$A8,'Cleaned Data'!$C:$C,M$3) -> 0 | N8: =SUM(B8:M8) -> 34000 | O8: =N8/$N$16 -> 0.029827178
A9: Healthcare | B9: =SUMIFS('Cleaned Data'!$J:$J,'Cleaned Data'!$I:$I,$A9,'Cleaned Data'!$C:$C,B$3) -> 0 | C9: =SUMIFS('Cleaned Data'!$J:$J,'Cleaned Data'!$I:$I,$A9,'Cleaned Data'!$C:$C,C$3) -> 0 | D9: =SUMIFS('Cleaned Data'!$J:$J,'Cleaned Data'!$I:$I,$A9,'Cleaned Data'!$C:$C,D$3) -> 6800 | E9: =SUMIFS('Cleaned Data'!$J:$J,'Cleaned Data'!$I:$I,$A9,'Cleaned Data'!$C:$C,E$3) -> 24600 | F9: =SUMIFS('Cleaned Data'!$J:$J,'Cleaned Data'!$I:$I,$A9,'Cleaned Data'!$C:$C,F$3) -> 0 | G9: =SUMIFS('Cleaned Data'!$J:$J,'Cleaned Data'!$I:$I,$A9,'Cleaned Data'!$C:$C,G$3) -> 2400 | H9: =SUMIFS('Cleaned Data'!$J:$J,'Cleaned Data'!$I:$I,$A9,'Cleaned Data'!$C:$C,H$3) -> 0 | I9: =SUMIFS('Cleaned Data'!$J:$J,'Cleaned Data'!$I:$I,$A9,'Cleaned Data'!$C:$C,I$3) -> 0 | ... M9: =SUMIFS('Cleaned Data'!$J:$J,'Cleaned Data'!$I:$I,$A9,'Cleaned Data'!$C:$C,M$3) -> 8300 | N9: =SUM(B9:M9) -> 56000 | O9: =N9/$N$16 -> 0.049127116
A10: Education | B10: =SUMIFS('Cleaned Data'!$J:$J,'Cleaned Data'!$I:$I,$A10,'Cleaned Data'!$C:$C,B$3) -> 6200 | C10: =SUMIFS('Cleaned Data'!$J:$J,'Cleaned Data'!$I:$I,$A10,'Cleaned Data'!$C:$C,C$3) -> 0 | D10: =SUMIFS('Cleaned Data'!$J:$J,'Cleaned Data'!$I:$I,$A10,'Cleaned Data'!$C:$C,D$3) -> 0 | E10: =SUMIFS('Cleaned Data'!$J:$J,'Cleaned Data'!$I:$I,$A10,'Cleaned Data'!$C:$C,E$3) -> 0 | F10: =SUMIFS('Cleaned Data'!$J:$J,'Cleaned Data'!$I:$I,$A10,'Cleaned Data'!$C:$C,F$3) -> 0 | G10: =SUMIFS('Cleaned Data'!$J:$J,'Cleaned Data'!$I:$I,$A10,'Cleaned Data'!$C:$C,G$3) -> 0 | H10: =SUMIFS('Cleaned Data'!$J:$J,'Cleaned Data'!$I:$I,$A10,'Cleaned Data'!$C:$C,H$3) -> 0 | I10: =SUMIFS('Cleaned Data'!$J:$J,'Cleaned Data'!$I:$I,$A10,'Cleaned Data'!$C:$C,I$3) -> 8300 | ... M10: =SUMIFS('Cleaned Data'!$J:$J,'Cleaned Data'!$I:$I,$A10,'Cleaned Data'!$C:$C,M$3) -> 5300 | N10: =SUM(B10:M10) -> 23700 | O10: =N10/$N$16 -> 0.020791297
A11: Shopping | B11: =SUMIFS('Cleaned Data'!$J:$J,'Cleaned Data'!$I:$I,$A11,'Cleaned Data'!$C:$C,B$3) -> 7400 | C11: =SUMIFS('Cleaned Data'!$J:$J,'Cleaned Data'!$I:$I,$A11,'Cleaned Data'!$C:$C,C$3) -> 0 | D11: =SUMIFS('Cleaned Data'!$J:$J,'Cleaned Data'!$I:$I,$A11,'Cleaned Data'!$C:$C,D$3) -> 0 | E11: =SUMIFS('Cleaned Data'!$J:$J,'Cleaned Data'!$I:$I,$A11,'Cleaned Data'!$C:$C,E$3) -> 0 | F11: =SUMIFS('Cleaned Data'!$J:$J,'Cleaned Data'!$I:$I,$A11,'Cleaned Data'!$C:$C,F$3) -> 16200 | G11: =SUMIFS('Cleaned Data'!$J:$J,'Cleaned Data'!$I:$I,$A11,'Cleaned Data'!$C:$C,G$3) -> 0 | H11: =SUMIFS('Cleaned Data'!$J:$J,'Cleaned Data'!$I:$I,$A11,'Cleaned Data'!$C:$C,H$3) -> 16000 | I11: =SUMIFS('Cleaned Data'!$J:$J,'Cleaned Data'!$I:$I,$A11,'Cleaned Data'!$C:$C,I$3) -> 8400 | ... M11: =SUMIFS('Cleaned Data'!$J:$J,'Cleaned Data'!$I:$I,$A11,'Cleaned Data'!$C:$C,M$3) -> 7200 | N11: =SUM(B11:M11) -> 78900 | O11: =N11/$N$16 -> 0.069216598
A12: Investment | B12: =SUMIFS('Cleaned Data'!$J:$J,'Cleaned Data'!$I:$I,$A12,'Cleaned Data'!$C:$C,B$3) -> 0 | C12: =SUMIFS('Cleaned Data'!$J:$J,'Cleaned Data'!$I:$I,$A12,'Cleaned Data'!$C:$C,C$3) -> 0 | D12: =SUMIFS('Cleaned Data'!$J:$J,'Cleaned Data'!$I:$I,$A12,'Cleaned Data'!$C:$C,D$3) -> 39000 | E12: =SUMIFS('Cleaned Data'!$J:$J,'Cleaned Data'!$I:$I,$A12,'Cleaned Data'!$C:$C,E$3) -> 41000 | F12: =SUMIFS('Cleaned Data'!$J:$J,'Cleaned Data'!$I:$I,$A12,'Cleaned Data'!$C:$C,F$3) -> 0 | G12: =SUMIFS('Cleaned Data'!$J:$J,'Cleaned Data'!$I:$I,$A12,'Cleaned Data'!$C:$C,G$3) -> 31000 | H12: =SUMIFS('Cleaned Data'!$J:$J,'Cleaned Data'!$I:$I,$A12,'Cleaned Data'!$C:$C,H$3) -> 0 | I12: =SUMIFS('Cleaned Data'!$J:$J,'Cleaned Data'!$I:$I,$A12,'Cleaned Data'!$C:$C,I$3) -> 35000 | ... M12: =SUMIFS('Cleaned Data'!$J:$J,'Cleaned Data'!$I:$I,$A12,'Cleaned Data'!$C:$C,M$3) -> 37000 | N12: =SUM(B12:M12) -> 344000 | O12: =N12/$N$16 -> 0.30178086
A13: Food | B13: =SUMIFS('Cleaned Data'!$J:$J,'Cleaned Data'!$I:$I,$A13,'Cleaned Data'!$C:$C,B$3) -> 0 | C13: =SUMIFS('Cleaned Data'!$J:$J,'Cleaned Data'!$I:$I,$A13,'Cleaned Data'!$C:$C,C$3) -> 0 | D13: =SUMIFS('Cleaned Data'!$J:$J,'Cleaned Data'!$I:$I,$A13,'Cleaned Data'!$C:$C,D$3) -> 13800 | E13: =SUMIFS('Cleaned Data'!$J:$J,'Cleaned Data'!$I:$I,$A13,'Cleaned Data'!$C:$C,E$3) -> 0 | F13: =SUMIFS('Cleaned Data'!$J:$J,'Cleaned Data'!$I:$I,$A13,'Cleaned Data'!$C:$C,F$3) -> 0 | G13: =SUMIFS('Cleaned Data'!$J:$J,'Cleaned Data'!$I:$I,$A13,'Cleaned Data'!$C:$C,G$3) -> 5900 | H13: =SUMIFS('Cleaned Data'!$J:$J,'Cleaned Data'!$I:$I,$A13,'Cleaned Data'!$C:$C,H$3) -> 0 | I13: =SUMIFS('Cleaned Data'!$J:$J,'Cleaned Data'!$I:$I,$A13,'Cleaned Data'!$C:$C,I$3) -> 6300 | ... M13: =SUMIFS('Cleaned Data'!$J:$J,'Cleaned Data'!$I:$I,$A13,'Cleaned Data'!$C:$C,M$3) -> 11400 | N13: =SUM(B13:M13) -> 41300 | O13: =N13/$N$16 -> 0.036231248
A14: Transport | B14: =SUMIFS('Cleaned Data'!$J:$J,'Cleaned Data'!$I:$I,$A14,'Cleaned Data'!$C:$C,B$3) -> 0 | C14: =SUMIFS('Cleaned Data'!$J:$J,'Cleaned Data'!$I:$I,$A14,'Cleaned Data'!$C:$C,C$3) -> 4300 | D14: =SUMIFS('Cleaned Data'!$J:$J,'Cleaned Data'!$I:$I,$A14,'Cleaned Data'!$C:$C,D$3) -> 0 | E14: =SUMIFS('Cleaned Data'!$J:$J,'Cleaned Data'!$I:$I,$A14,'Cleaned Data'!$C:$C,E$3) -> 4800 | F14: =SUMIFS('Cleaned Data'!$J:$J,'Cleaned Data'!$I:$I,$A14,'Cleaned Data'!$C:$C,F$3) -> 9200 | G14: =SUMIFS('Cleaned Data'!$J:$J,'Cleaned Data'!$I:$I,$A14,'Cleaned Data'!$C:$C,G$3) -> 4800 | H14: =SUMIFS('Cleaned Data'!$J:$J,'Cleaned Data'!$I:$I,$A14,'Cleaned Data'!$C:$C,H$3) -> 0 | I14: =SUMIFS('Cleaned Data'!$J:$J,'Cleaned Data'!$I:$I,$A14,'Cleaned Data'!$C:$C,I$3) -> 0 | ... M14: =SUMIFS('Cleaned Data'!$J:$J,'Cleaned Data'!$I:$I,$A14,'Cleaned Data'!$C:$C,M$3) -> 0 | N14: =SUM(B14:M14) -> 23100 | O14: =N14/$N$16 -> 0.020264936
A15: Travel | B15: =SUMIFS('Cleaned Data'!$J:$J,'Cleaned Data'!$I:$I,$A15,'Cleaned Data'!$C:$C,B$3) -> 0 | C15: =SUMIFS('Cleaned Data'!$J:$J,'Cleaned Data'!$I:$I,$A15,'Cleaned Data'!$C:$C,C$3) -> 19500 | D15: =SUMIFS('Cleaned Data'!$J:$J,'Cleaned Data'!$I:$I,$A15,'Cleaned Data'!$C:$C,D$3) -> 0 | E15: =SUMIFS('Cleaned Data'!$J:$J,'Cleaned Data'!$I:$I,$A15,'Cleaned Data'!$C:$C,E$3) -> 0 | F15: =SUMIFS('Cleaned Data'!$J:$J,'Cleaned Data'!$I:$I,$A15,'Cleaned Data'!$C:$C,F$3) -> 0 | G15: =SUMIFS('Cleaned Data'!$J:$J,'Cleaned Data'!$I:$I,$A15,'Cleaned Data'!$C:$C,G$3) -> 0 | H15: =SUMIFS('Cleaned Data'!$J:$J,'Cleaned Data'!$I:$I,$A15,'Cleaned Data'!$C:$C,H$3) -> 0 | I15: =SUMIFS('Cleaned Data'!$J:$J,'Cleaned Data'!$I:$I,$A15,'Cleaned Data'!$C:$C,I$3) -> 10400 | ... M15: =SUMIFS('Cleaned Data'!$J:$J,'Cleaned Data'!$I:$I,$A15,'Cleaned Data'!$C:$C,M$3) -> 0 | N15: =SUM(B15:M15) -> 70200 | O15: =N15/$N$16 -> 0.06158435
A16: TOTAL | B16: =SUM(B4:B15) -> 112500 | C16: =SUM(C4:C15) -> 99100 | D16: =SUM(D4:D15) -> 71700 | E16: =SUM(E4:E15) -> 81700 | F16: =SUM(F4:F15) -> 50100 | G16: =SUM(G4:G15) -> 109500 | H16: =SUM(H4:H15) -> 103300 | I16: =SUM(I4:I15) -> 118900 | ... N16: =SUM(N4:N15) -> 1139900 | O16: =N16/$N$16 -> 1

Sheet Budget Analysis
A1: 🏦 BUDGET ANALYSIS — PLANNED vs ACTUAL SPENDING
A2: ▌ SET YOUR BUDGET TARGETS BELOW (Blue = Input Cells — change freely)
A3: Expense Category | B3: Monthly Budget (₹) | C3: Actual (₹) | D3: Variance (₹) | E3: Var % | F3: Status
A4: Investment | B4: 412800 | C4: =SUMIF('Cleaned Data'!I3:I100,'Budget Analysis'!A4,'Cleaned Data'!J3:J100) -> 344000 | D4: =B4-C4 -> 68800 | E4: =IF(B4=0,0,(B4-C4)/B4) -> 0.16666667 | F4: =IF(D4>=0,"✅ Under Budget","⚠️ Over Budget") -> ✅ Under Budget
A5: Rent | B5: 362400 | C5: =SUMIF('Cleaned Data'!I4:I101,'Budget Analysis'!A5,'Cleaned Data'!J4:J101) -> 309000 | D5: =B5-C5 -> 53400 | E5: =IF(B5=0,0,(B5-C5)/B5) -> 0.14735099 | F5: =IF(D5>=0,"✅ Under Budget","⚠️ Over Budget") -> ✅ Under Budget
A6: Shopping | B6: 94700 | C6: =SUMIF('Cleaned Data'!I5:I102,'Budget Analysis'!A6,'Cleaned Data'!J5:J102) -> 78900 | D6: =B6-C6 -> 15800 | E6: =IF(B6=0,0,(B6-C6)/B6) -> 0.16684266 | F6: =IF(D6>=0,"✅ Under Budget","⚠️ Over Budget") -> ✅ Under Budget
A7: Travel | B7: 60000 | C7: =SUMIF('Cleaned Data'!I6:I103,'Budget Analysis'!A7,'Cleaned Data'!J6:J103) -> 70200 | D7: =B7-C7 -> -10200 | E7: =IF(B7=0,0,(B7-C7)/B7) -> -0.17 | F7: =IF(D7>=0,"✅ Under Budget","⚠️ Over Budget") -> ⚠️ Over Budget
A8: Unknown | B8: 70100 | C8: =SUMIF('Cleaned Data'!I7:I104,'Budget Analysis'!A8,'Cleaned Data'!J7:J104) -> 55200 | D8: =B8-C8 -> 14900 | E8: =IF(B8=0,0,(B8-C8)/B8) -> 0.2125535 | F8: =IF(D8>=0,"✅ Under Budget","⚠️ Over Budget") -> ✅ Under Budget
A9: Healthcare | B9: 67200 | C9: =SUMIF('Cleaned Data'!I8:I105,'Budget Analysis'!A9,'Cleaned Data'!J8:J105) -> 56000 | D9: =B9-C9 -> 11200 | E9: =IF(B9=0,0,(B9-C9)/B9) -> 0.16666667 | F9: =IF(D9>=0,"✅ Under Budget","⚠️ Over Budget") -> ✅ Under Budget
A10: Utilities | B10: 35000 | C10: =SUMIF('Cleaned Data'!I9:I106,'Budget Analysis'!A10,'Cleaned Data'!J9:J106) -> 39400 | D10: =B10-C10 -> -4400 | E10: =IF(B10=0,0,(B10-C10)/B10) -> -0.12571429 | F10: =IF(D10>=0,"✅ Under Budget","⚠️ Over Budget") -> ⚠️ Over Budget
A11: Food | B11: 49600 | C11: =SUMIF('Cleaned Data'!I10:I107,'Budget Analysis'!A11,'Cleaned Data'!J10:J107) -> 41300 | D11: =B11-C11 -> 8300 | E11: =IF(B11=0,0,(B11-C11)/B11) -> 0.16733871 | F11: =IF(D11>=0,"✅ Under Budget","⚠️ Over Budget") -> ✅ Under Budget
A12: Groceries | B12: 46200 | C12: =SUMIF('Cleaned Data'!I11:I108,'Budget Analysis'!A12,'Cleaned Data'!J11:J108) -> 32000 | D12: =B12-C12 -> 14200 | E12: =IF(B12=0,0,(B12-C12)/B12) -> 0.30735931 | F12: =IF(D12>=0,"✅ Under Budget","⚠️ Over Budget") -> ✅ Under Budget
A13: Entertainment | B13: 20000 | C13: =SUMIF('Cleaned Data'!I12:I109,'Budget Analysis'!A13,'Cleaned Data'!J12:J109) -> 26400 | D13: =B13-C13 -> -6400 | E13: =IF(B13=0,0,(B13-C13)/B13) -> -0.32 | F13: =IF(D13>=0,"✅ Under Budget","⚠️ Over Budget") -> ⚠️ Over Budget
A14: Education | B14: 28400 | C14: =SUMIF('Cleaned Data'!I13:I110,'Budget Analysis'!A14,'Cleaned Data'!J13:J110) -> 19200 | D14: =B14-C14 -> 9200 | E14: =IF(B14=0,0,(B14-C14)/B14) -> 0.32394366 | F14: =IF(D14>=0,"✅ Under Budget","⚠️ Over Budget") -> ✅ Under Budget
A15: Transport | B15: 27700 | C15: =SUMIF('Cleaned Data'!I14:I111,'Budget Analysis'!A15,'Cleaned Data'!J14:J111) -> 23100 | D15: =B15-C15 -> 4600 | E15: =IF(B15=0,0,(B15-C15)/B15) -> 0.16606498 | F15: =IF(D15>=0,"✅ Under Budget","⚠️ Over Budget") -> ✅ Under Budget
A16: TOTAL | B16: =SUM(B4:B15) -> 1274100 | C16: =SUM(C4:C15) -> 1094700 | D16: =SUM(D4:D15) -> 179400 | E16: =IF(B16=0,0,(B16-C16)/B16) -> 0.14080527

Sheet Pivot Analysis
A1: PIVOT ANALYSIS | L1: Go to Welcome Page
A3: Month | B3: Total Income | C3: Total Expense | D3: Total Savings | E3: EMI | F3: Net Surplus | H3: Expense Category | I3: Amount | K3: Income Source | L3: Total Income
A4: January | B4: 605000 | C4: 112500 | D4: 106700 | E4: 45300 | F4: =B4-(C4+D4+E4) -> 340500 | H4: Investment | I4: 344000 | K4: Salary | L4: 3235000
A5: February | B5: 681000 | C5: 99100 | D5: 148000 | E5: 63000 | F5: =B5-(C5+D5+E5) -> 370900 | H5: Rent | I5: 302000 | K5: Business | L5: 2487000
A6: March | B6: 570000 | C6: 71700 | D6: 120200 | E6: 42000 | F6: =B6-(C6+D6+E6) -> 336100 | H6: Shopping | I6: 78900 | K6: Freelancing | L6: 992000
A7: April | B7: 817000 | C7: 81700 | D7: 220000 | E7: 73000 | F7: =B7-(C7+D7+E7) -> 442300 | H7: Travel | I7: 70200 | K7: Unknown | L7: 916000
A8: May | B8: 552000 | C8: 50100 | D8: 90500 | E8: 37000 | F8: =B8-(C8+D8+E8) -> 374400 | H8: Unknown | I8: 58400 | K8: Internship | L8: 176000
A9: June | B9: 639000 | C9: 109500 | D9: 141500 | E9: 50000 | F9: =B9-(C9+D9+E9) -> 338000 | H9: Healthcare | I9: 56000 | K9: Salary | L9: 65000
A10: July | B10: 731000 | C10: 103300 | D10: 180500 | E10: 81000 | F10: =B10-(C10+D10+E10) -> 366200 | H10: Utilities | I10: 44800
A11: August | B11: 630000 | C11: 118900 | D11: 145500 | E11: 60000 | F11: =B11-(C11+D11+E11) -> 305600 | H11: Food | I11: 41300
A12: September | B12: 661000 | C12: 95000 | D12: 142000 | E12: 61000 | F12: =B12-(C12+D12+E12) -> 363000 | H12: Groceries | I12: 38500
A13: October | B13: 465000 | C13: 67500 | D13: 73500 | E13: 38000 | F13: =B13-(C13+D13+E13) -> 286000 | H13: Entertainment | I13: 34000
A14: November | B14: 825000 | C14: 148300 | D14: 211000 | E14: 84000 | F14: =B14-(C14+D14+E14) -> 381700 | H14: Education | I14: 23700
A15: December | B15: 695000 | C15: 82300 | D15: 167500 | E15: 61500 | F15: =B15-(C15+D15+E15) -> 383700 | H15: Transport | I15: 23100
A16: TOTAL | B16: =SUM(B4:B15) -> 7871000 | C16: =SUM(C4:C15) -> 1139900 | D16: =SUM(D4:D15) -> 1746900 | E16: =SUM(E4:E15) -> 695800 | F16: =SUM(F4:F15) -> 4288400

Sheet Final Dashboard
B2: 💰 PERSONAL FINANCE & BUDGET PLANNER | EXECUTIVE DASHBOARD | N2: Go to Welcome page
B3: Real-time KPI Tracker · 100 Transactions · Multiple Cities · FY 2024–25
B4: ▌ KEY PERFORMANCE INDICATORS
B6: 📈 TOTAL INCOME | F6: 📉 TOTAL EXPENSES | J6: 🏦 TOTAL SAVINGS
B7: ='Income Analysis'!N10 -> 7871000 | F7: ='Pivot Analysis'!C16+'Pivot Analysis'!E16 -> 1835700 | J7: ='Pivot Analysis'!D16 -> 1746900
B8: Across All Sources | F8: All Categories | J8: Net Accumulated
B10: 🏠 LOAN EMI | F10: ⭐ AVG CREDIT SCORE | J10: 💹 SAVINGS RATE
B11: ='Pivot Analysis'!E16 -> 695800 | F11: =AVERAGE('Cleaned Data'!N3:N100) -> 736.55102 | J11: =((B7-F7)/B7) -> 0.76677678
B12: Total EMI Paid | F12: Portfolio Average | J12: Income → Savings
B14: ⚠️ EXPENSE RATIO | F14: 📊 TRANSACTIONS | J14: 👤 AVG INCOME
B15: =(F7/B7) -> 0.23322322 | F15: =COUNTA('Cleaned Data'!A3:A100) -> 98 | J15: =B7/F15 -> 80316.327
B16: Income Spent | F16: Total Records | J16: Per Person
B18: ▌ INTERACTIVE ANALYSIS — MONTHLY INCOME vs EXPENSE vs SAVINGS
I38: ▌ FINANCIAL STATUS DISTRIBUTION
I39: Status | L39: Count
I40: ● Excellent | L40: =COUNTIF('Cleaned Data'!O3:O100,"Excellent") -> 21
I41: ● Good | L41: =COUNTIF('Cleaned Data'!O3:O100,"Good") -> 34
I42: ● Stable | L42: =COUNTIF('Cleaned Data'!O3:O100,"Stable") -> 21
I43: ● Average | L43: =COUNTIF('Cleaned Data'!O3:O100,"Average") -> 19
I44: ● Risky | L44: =COUNTIF('Cleaned Data'!O3:O100,"Risky") -> 3
I47: ▌ TOP CITIES — TOTAL SAVINGS (₹)
I48: City | L48: Total Savings (₹)
I49: Kolkata | L49: 353900
I50: Delhi | L50: 340500
I51: Ahmedabad | L51: 215000
I52: Bangalore | L52: 191000
I53: Mumbai | L53: 182000
I54: Unknown | L54: 135500
I55: Chennai | L55: 80000
I56: Patna | L56: 61000
B57: Dashboard auto-calculates from Cleaned Data sheet | Presented by Abhijit Roy & Aakash Nath | © 2025 Personal Finance Planner
